{
  "header": {
    "author": "zji@ucar.edu",
    "date": "2023-12-26",
    "description": "Auto-generated"
  },
  "database": "upadb",
  "schema": "obsua",
  "name": "ghcn_dly_means_longterm",
  "pkey": "recid",
  "column": [
    {
      "name": "recid",
      "type": "serial",
      "notnull": "NOT NULL",
      "comment": "autoincrement field"
    },
    {
      "name": "id",
      "type": "varchar(50)",
      "comment": "WMO or WBAN id (general 4-6 digits)"
    },
    {
      "name": "idflag",
      "type": "smallint",
      "comment": " Flag to indicate if id is WMO,WBAN or other"
    },
    {
      "name": "parm",
      "type": "char(4)",
      "comment": " ghcm variable name (TMIN,TMAX,PRCP,SNOW,SNWD,...)"
    },
    {
      "name": "jan",
      "type": "double precision"
    },
    {
      "name": "feb",
      "type": "double precision"
    },
    {
      "name": "mar",
      "type": "double precision"
    },
    {
      "name": "apr",
      "type": "double precision"
    },
    {
      "name": "may",
      "type": "double precision"
    },
    {
      "name": "jun",
      "type": "double precision"
    },
    {
      "name": "jul",
      "type": "double precision"
    },
    {
      "name": "aug",
      "type": "double precision"
    },
    {
      "name": "sep",
      "type": "double precision"
    },
    {
      "name": "oct",
      "type": "double precision"
    },
    {
      "name": "nov",
      "type": "double precision"
    },
    {
      "name": "dcm",
      "type": "double precision"
    },
    {
      "name": "ann",
      "type": "double precision",
      "comment": " annual mean"
    },
    {
      "name": "jancnt",
      "type": "int"
    },
    {
      "name": "febcnt",
      "type": "int"
    },
    {
      "name": "marcnt",
      "type": "int"
    },
    {
      "name": "aprcnt",
      "type": "int"
    },
    {
      "name": "maycnt",
      "type": "int"
    },
    {
      "name": "juncnt",
      "type": "int"
    },
    {
      "name": "julcnt",
      "type": "int"
    },
    {
      "name": "augcnt",
      "type": "int"
    },
    {
      "name": "sepcnt",
      "type": "int"
    },
    {
      "name": "octcnt",
      "type": "int"
    },
    {
      "name": "novcnt",
      "type": "int"
    },
    {
      "name": "deccnt",
      "type": "int"
    },
    {
      "name": "anncnt",
      "type": "int"
    },
    {
      "name": "dly",
      "type": "text",
      "comment": " daily"
    }
  ],
  "index": [
    {
      "name": "ghcn_dly_means_longterm_idx_1",
      "column": "id"
    },
    {
      "name": "ghcn_dly_means_longterm_idx_2",
      "column": "parm"
    },
    {
      "name": "ghcn_dly_means_longterm_idx_4",
      "column": "id,parm"
    }
  ]
}