{
  "Name": "appstream",
  "Actions": [
    {
      "Name": "AssociateAppBlockBuilderAppBlock",
      "ActionConditionKeys": [
        "aws:ResourceTag/${TagKey}"
      ],
      "Annotations": {
        "Properties": {
          "IsList": false,
          "IsPermissionManagement": false,
          "IsTaggingOnly": false,
          "IsWrite": true
        }
      },
      "Resources": [
        {
          "Name": "app-block"
        },
        {
          "Name": "app-block-builder"
        }
      ],
      "SupportedBy": {
        "IAM Access Analyzer Policy Generation": true,
        "IAM Action Last Accessed": true
      }
    },
    {
      "Name": "AssociateApplicationFleet",
      "ActionConditionKeys": [
        "aws:ResourceTag/${TagKey}"
      ],
      "Annotations": {
        "Properties": {
          "IsList": false,
          "IsPermissionManagement": false,
          "IsTaggingOnly": false,
          "IsWrite": true
        }
      },
      "Resources": [
        {
          "Name": "application"
        },
        {
          "Name": "fleet"
        }
      ],
      "SupportedBy": {
        "IAM Access Analyzer Policy Generation": true,
        "IAM Action Last Accessed": true
      }
    },
    {
      "Name": "AssociateApplicationToEntitlement",
      "Annotations": {
        "Properties": {
          "IsList": false,
          "IsPermissionManagement": false,
          "IsTaggingOnly": false,
          "IsWrite": true
        }
      },
      "Resources": [
        {
          "Name": "stack"
        }
      ],
      "SupportedBy": {
        "IAM Access Analyzer Policy Generation": true,
        "IAM Action Last Accessed": true
      }
    },
    {
      "Name": "AssociateFleet",
      "ActionConditionKeys": [
        "aws:ResourceTag/${TagKey}"
      ],
      "Annotations": {
        "Properties": {
          "IsList": false,
          "IsPermissionManagement": false,
          "IsTaggingOnly": false,
          "IsWrite": true
        }
      },
      "Resources": [
        {
          "Name": "fleet"
        },
        {
          "Name": "stack"
        }
      ],
      "SupportedBy": {
        "IAM Access Analyzer Policy Generation": true,
        "IAM Action Last Accessed": true
      }
    },
    {
      "Name": "BatchAssociateUserStack",
      "ActionConditionKeys": [
        "aws:ResourceTag/${TagKey}"
      ],
      "Annotations": {
        "Properties": {
          "IsList": false,
          "IsPermissionManagement": false,
          "IsTaggingOnly": false,
          "IsWrite": true
        }
      },
      "Resources": [
        {
          "Name": "stack"
        }
      ],
      "SupportedBy": {
        "IAM Access Analyzer Policy Generation": true,
        "IAM Action Last Accessed": true
      }
    },
    {
      "Name": "BatchDisassociateUserStack",
      "ActionConditionKeys": [
        "aws:ResourceTag/${TagKey}"
      ],
      "Annotations": {
        "Properties": {
          "IsList": false,
          "IsPermissionManagement": false,
          "IsTaggingOnly": false,
          "IsWrite": true
        }
      },
      "Resources": [
        {
          "Name": "stack"
        }
      ],
      "SupportedBy": {
        "IAM Access Analyzer Policy Generation": true,
        "IAM Action Last Accessed": true
      }
    },
    {
      "Name": "CopyImage",
      "ActionConditionKeys": [
        "aws:ResourceTag/${TagKey}"
      ],
      "Annotations": {
        "Properties": {
          "IsList": false,
          "IsPermissionManagement": false,
          "IsTaggingOnly": false,
          "IsWrite": true
        }
      },
      "Resources": [
        {
          "Name": "image"
        }
      ],
      "SupportedBy": {
        "IAM Access Analyzer Policy Generation": true,
        "IAM Action Last Accessed": true
      }
    },
    {
      "Name": "CreateAppBlock",
      "ActionConditionKeys": [
        "aws:RequestTag/${TagKey}",
        "aws:ResourceTag/${TagKey}",
        "aws:TagKeys"
      ],
      "Annotations": {
        "Properties": {
          "IsList": false,
          "IsPermissionManagement": false,
          "IsTaggingOnly": false,
          "IsWrite": true
        }
      },
      "SupportedBy": {
        "IAM Access Analyzer Policy Generation": true,
        "IAM Action Last Accessed": true
      }
    },
    {
      "Name": "CreateAppBlockBuilder",
      "ActionConditionKeys": [
        "aws:RequestTag/${TagKey}",
        "aws:TagKeys"
      ],
      "Annotations": {
        "Properties": {
          "IsList": false,
          "IsPermissionManagement": false,
          "IsTaggingOnly": false,
          "IsWrite": true
        }
      },
      "Resources": [
        {
          "Name": "app-block-builder"
        }
      ],
      "SupportedBy": {
        "IAM Access Analyzer Policy Generation": true,
        "IAM Action Last Accessed": true
      }
    },
    {
      "Name": "CreateAppBlockBuilderStreamingURL",
      "ActionConditionKeys": [
        "aws:ResourceTag/${TagKey}"
      ],
      "Annotations": {
        "Properties": {
          "IsList": false,
          "IsPermissionManagement": false,
          "IsTaggingOnly": false,
          "IsWrite": true
        }
      },
      "Resources": [
        {
          "Name": "app-block-builder"
        }
      ],
      "SupportedBy": {
        "IAM Access Analyzer Policy Generation": true,
        "IAM Action Last Accessed": true
      }
    },
    {
      "Name": "CreateApplication",
      "ActionConditionKeys": [
        "aws:RequestTag/${TagKey}",
        "aws:ResourceTag/${TagKey}",
        "aws:TagKeys"
      ],
      "Annotations": {
        "Properties": {
          "IsList": false,
          "IsPermissionManagement": false,
          "IsTaggingOnly": false,
          "IsWrite": true
        }
      },
      "Resources": [
        {
          "Name": "app-block"
        }
      ],
      "SupportedBy": {
        "IAM Access Analyzer Policy Generation": true,
        "IAM Action Last Accessed": true
      }
    },
    {
      "Name": "CreateDirectoryConfig",
      "Annotations": {
        "Properties": {
          "IsList": false,
          "IsPermissionManagement": false,
          "IsTaggingOnly": false,
          "IsWrite": true
        }
      },
      "SupportedBy": {
        "IAM Access Analyzer Policy Generation": true,
        "IAM Action Last Accessed": true
      }
    },
    {
      "Name": "CreateEntitlement",
      "Annotations": {
        "Properties": {
          "IsList": false,
          "IsPermissionManagement": false,
          "IsTaggingOnly": false,
          "IsWrite": true
        }
      },
      "Resources": [
        {
          "Name": "stack"
        }
      ],
      "SupportedBy": {
        "IAM Access Analyzer Policy Generation": true,
        "IAM Action Last Accessed": true
      }
    },
    {
      "Name": "CreateFleet",
      "ActionConditionKeys": [
        "aws:RequestTag/${TagKey}",
        "aws:TagKeys"
      ],
      "Annotations": {
        "Properties": {
          "IsList": false,
          "IsPermissionManagement": false,
          "IsTaggingOnly": false,
          "IsWrite": true
        }
      },
      "Resources": [
        {
          "Name": "fleet"
        },
        {
          "Name": "image"
        }
      ],
      "SupportedBy": {
        "IAM Access Analyzer Policy Generation": true,
        "IAM Action Last Accessed": true
      }
    },
    {
      "Name": "CreateImageBuilder",
      "ActionConditionKeys": [
        "aws:RequestTag/${TagKey}",
        "aws:TagKeys"
      ],
      "Annotations": {
        "Properties": {
          "IsList": false,
          "IsPermissionManagement": false,
          "IsTaggingOnly": false,
          "IsWrite": true
        }
      },
      "Resources": [
        {
          "Name": "image"
        },
        {
          "Name": "image-builder"
        }
      ],
      "SupportedBy": {
        "IAM Access Analyzer Policy Generation": true,
        "IAM Action Last Accessed": true
      }
    },
    {
      "Name": "CreateImageBuilderStreamingURL",
      "ActionConditionKeys": [
        "aws:ResourceTag/${TagKey}"
      ],
      "Annotations": {
        "Properties": {
          "IsList": false,
          "IsPermissionManagement": false,
          "IsTaggingOnly": false,
          "IsWrite": true
        }
      },
      "Resources": [
        {
          "Name": "image-builder"
        }
      ],
      "SupportedBy": {
        "IAM Access Analyzer Policy Generation": true,
        "IAM Action Last Accessed": true
      }
    },
    {
      "Name": "CreateStack",
      "ActionConditionKeys": [
        "aws:RequestTag/${TagKey}",
        "aws:TagKeys"
      ],
      "Annotations": {
        "Properties": {
          "IsList": false,
          "IsPermissionManagement": false,
          "IsTaggingOnly": false,
          "IsWrite": true
        }
      },
      "Resources": [
        {
          "Name": "stack"
        }
      ],
      "SupportedBy": {
        "IAM Access Analyzer Policy Generation": true,
        "IAM Action Last Accessed": true
      }
    },
    {
      "Name": "CreateStreamingURL",
      "ActionConditionKeys": [
        "aws:ResourceTag/${TagKey}"
      ],
      "Annotations": {
        "Properties": {
          "IsList": false,
          "IsPermissionManagement": false,
          "IsTaggingOnly": false,
          "IsWrite": true
        }
      },
      "Resources": [
        {
          "Name": "fleet"
        },
        {
          "Name": "stack"
        }
      ],
      "SupportedBy": {
        "IAM Access Analyzer Policy Generation": true,
        "IAM Action Last Accessed": true
      }
    },
    {
      "Name": "CreateThemeForStack",
      "Annotations": {
        "Properties": {
          "IsList": false,
          "IsPermissionManagement": false,
          "IsTaggingOnly": false,
          "IsWrite": true
        }
      },
      "Resources": [
        {
          "Name": "stack"
        }
      ],
      "SupportedBy": {
        "IAM Access Analyzer Policy Generation": true,
        "IAM Action Last Accessed": true
      }
    },
    {
      "Name": "CreateUpdatedImage",
      "ActionConditionKeys": [
        "aws:RequestTag/${TagKey}",
        "aws:ResourceTag/${TagKey}",
        "aws:TagKeys"
      ],
      "Annotations": {
        "Properties": {
          "IsList": false,
          "IsPermissionManagement": false,
          "IsTaggingOnly": false,
          "IsWrite": true
        }
      },
      "Resources": [
        {
          "Name": "image"
        }
      ],
      "SupportedBy": {
        "IAM Access Analyzer Policy Generation": true,
        "IAM Action Last Accessed": true
      }
    },
    {
      "Name": "CreateUsageReportSubscription",
      "Annotations": {
        "Properties": {
          "IsList": false,
          "IsPermissionManagement": false,
          "IsTaggingOnly": false,
          "IsWrite": true
        }
      },
      "SupportedBy": {
        "IAM Access Analyzer Policy Generation": true,
        "IAM Action Last Accessed": true
      }
    },
    {
      "Name": "CreateUser",
      "Annotations": {
        "Properties": {
          "IsList": false,
          "IsPermissionManagement": false,
          "IsTaggingOnly": false,
          "IsWrite": true
        }
      },
      "SupportedBy": {
        "IAM Access Analyzer Policy Generation": true,
        "IAM Action Last Accessed": true
      }
    },
    {
      "Name": "DeleteAppBlock",
      "ActionConditionKeys": [
        "aws:ResourceTag/${TagKey}"
      ],
      "Annotations": {
        "Properties": {
          "IsList": false,
          "IsPermissionManagement": false,
          "IsTaggingOnly": false,
          "IsWrite": true
        }
      },
      "Resources": [
        {
          "Name": "app-block"
        }
      ],
      "SupportedBy": {
        "IAM Access Analyzer Policy Generation": true,
        "IAM Action Last Accessed": true
      }
    },
    {
      "Name": "DeleteAppBlockBuilder",
      "ActionConditionKeys": [
        "aws:ResourceTag/${TagKey}"
      ],
      "Annotations": {
        "Properties": {
          "IsList": false,
          "IsPermissionManagement": false,
          "IsTaggingOnly": false,
          "IsWrite": true
        }
      },
      "Resources": [
        {
          "Name": "app-block-builder"
        }
      ],
      "SupportedBy": {
        "IAM Access Analyzer Policy Generation": true,
        "IAM Action Last Accessed": true
      }
    },
    {
      "Name": "DeleteApplication",
      "ActionConditionKeys": [
        "aws:ResourceTag/${TagKey}"
      ],
      "Annotations": {
        "Properties": {
          "IsList": false,
          "IsPermissionManagement": false,
          "IsTaggingOnly": false,
          "IsWrite": true
        }
      },
      "Resources": [
        {
          "Name": "application"
        }
      ],
      "SupportedBy": {
        "IAM Access Analyzer Policy Generation": true,
        "IAM Action Last Accessed": true
      }
    },
    {
      "Name": "DeleteDirectoryConfig",
      "Annotations": {
        "Properties": {
          "IsList": false,
          "IsPermissionManagement": false,
          "IsTaggingOnly": false,
          "IsWrite": true
        }
      },
      "SupportedBy": {
        "IAM Access Analyzer Policy Generation": true,
        "IAM Action Last Accessed": true
      }
    },
    {
      "Name": "DeleteEntitlement",
      "Annotations": {
        "Properties": {
          "IsList": false,
          "IsPermissionManagement": false,
          "IsTaggingOnly": false,
          "IsWrite": true
        }
      },
      "Resources": [
        {
          "Name": "stack"
        }
      ],
      "SupportedBy": {
        "IAM Access Analyzer Policy Generation": true,
        "IAM Action Last Accessed": true
      }
    },
    {
      "Name": "DeleteFleet",
      "ActionConditionKeys": [
        "aws:ResourceTag/${TagKey}"
      ],
      "Annotations": {
        "Properties": {
          "IsList": false,
          "IsPermissionManagement": false,
          "IsTaggingOnly": false,
          "IsWrite": true
        }
      },
      "Resources": [
        {
          "Name": "fleet"
        }
      ],
      "SupportedBy": {
        "IAM Access Analyzer Policy Generation": true,
        "IAM Action Last Accessed": true
      }
    },
    {
      "Name": "DeleteImage",
      "ActionConditionKeys": [
        "aws:ResourceTag/${TagKey}"
      ],
      "Annotations": {
        "Properties": {
          "IsList": false,
          "IsPermissionManagement": false,
          "IsTaggingOnly": false,
          "IsWrite": true
        }
      },
      "Resources": [
        {
          "Name": "image"
        }
      ],
      "SupportedBy": {
        "IAM Access Analyzer Policy Generation": true,
        "IAM Action Last Accessed": true
      }
    },
    {
      "Name": "DeleteImageBuilder",
      "ActionConditionKeys": [
        "aws:ResourceTag/${TagKey}"
      ],
      "Annotations": {
        "Properties": {
          "IsList": false,
          "IsPermissionManagement": false,
          "IsTaggingOnly": false,
          "IsWrite": true
        }
      },
      "Resources": [
        {
          "Name": "image-builder"
        }
      ],
      "SupportedBy": {
        "IAM Access Analyzer Policy Generation": true,
        "IAM Action Last Accessed": true
      }
    },
    {
      "Name": "DeleteImagePermissions",
      "ActionConditionKeys": [
        "aws:ResourceTag/${TagKey}"
      ],
      "Annotations": {
        "Properties": {
          "IsList": false,
          "IsPermissionManagement": false,
          "IsTaggingOnly": false,
          "IsWrite": true
        }
      },
      "Resources": [
        {
          "Name": "image"
        }
      ],
      "SupportedBy": {
        "IAM Access Analyzer Policy Generation": true,
        "IAM Action Last Accessed": true
      }
    },
    {
      "Name": "DeleteStack",
      "ActionConditionKeys": [
        "aws:ResourceTag/${TagKey}"
      ],
      "Annotations": {
        "Properties": {
          "IsList": false,
          "IsPermissionManagement": false,
          "IsTaggingOnly": false,
          "IsWrite": true
        }
      },
      "Resources": [
        {
          "Name": "stack"
        }
      ],
      "SupportedBy": {
        "IAM Access Analyzer Policy Generation": true,
        "IAM Action Last Accessed": true
      }
    },
    {
      "Name": "DeleteThemeForStack",
      "Annotations": {
        "Properties": {
          "IsList": false,
          "IsPermissionManagement": false,
          "IsTaggingOnly": false,
          "IsWrite": true
        }
      },
      "Resources": [
        {
          "Name": "stack"
        }
      ],
      "SupportedBy": {
        "IAM Access Analyzer Policy Generation": true,
        "IAM Action Last Accessed": true
      }
    },
    {
      "Name": "DeleteUsageReportSubscription",
      "Annotations": {
        "Properties": {
          "IsList": false,
          "IsPermissionManagement": false,
          "IsTaggingOnly": false,
          "IsWrite": true
        }
      },
      "SupportedBy": {
        "IAM Access Analyzer Policy Generation": true,
        "IAM Action Last Accessed": true
      }
    },
    {
      "Name": "DeleteUser",
      "Annotations": {
        "Properties": {
          "IsList": false,
          "IsPermissionManagement": false,
          "IsTaggingOnly": false,
          "IsWrite": true
        }
      },
      "SupportedBy": {
        "IAM Access Analyzer Policy Generation": true,
        "IAM Action Last Accessed": true
      }
    },
    {
      "Name": "DescribeAppBlockBuilderAppBlockAssociations",
      "Annotations": {
        "Properties": {
          "IsList": true,
          "IsPermissionManagement": false,
          "IsTaggingOnly": false,
          "IsWrite": false
        }
      },
      "Resources": [
        {
          "Name": "app-block"
        },
        {
          "Name": "app-block-builder"
        }
      ],
      "SupportedBy": {
        "IAM Access Analyzer Policy Generation": true,
        "IAM Action Last Accessed": true
      }
    },
    {
      "Name": "DescribeAppBlockBuilders",
      "Annotations": {
        "Properties": {
          "IsList": true,
          "IsPermissionManagement": false,
          "IsTaggingOnly": false,
          "IsWrite": false
        }
      },
      "SupportedBy": {
        "IAM Access Analyzer Policy Generation": true,
        "IAM Action Last Accessed": true
      }
    },
    {
      "Name": "DescribeAppBlocks",
      "Annotations": {
        "Properties": {
          "IsList": true,
          "IsPermissionManagement": false,
          "IsTaggingOnly": false,
          "IsWrite": false
        }
      },
      "SupportedBy": {
        "IAM Access Analyzer Policy Generation": true,
        "IAM Action Last Accessed": true
      }
    },
    {
      "Name": "DescribeApplicationFleetAssociations",
      "Annotations": {
        "Properties": {
          "IsList": true,
          "IsPermissionManagement": false,
          "IsTaggingOnly": false,
          "IsWrite": false
        }
      },
      "Resources": [
        {
          "Name": "application"
        },
        {
          "Name": "fleet"
        }
      ],
      "SupportedBy": {
        "IAM Access Analyzer Policy Generation": true,
        "IAM Action Last Accessed": true
      }
    },
    {
      "Name": "DescribeApplications",
      "Annotations": {
        "Properties": {
          "IsList": true,
          "IsPermissionManagement": false,
          "IsTaggingOnly": false,
          "IsWrite": false
        }
      },
      "SupportedBy": {
        "IAM Access Analyzer Policy Generation": true,
        "IAM Action Last Accessed": true
      }
    },
    {
      "Name": "DescribeDirectoryConfigs",
      "Annotations": {
        "Properties": {
          "IsList": true,
          "IsPermissionManagement": false,
          "IsTaggingOnly": false,
          "IsWrite": false
        }
      },
      "SupportedBy": {
        "IAM Access Analyzer Policy Generation": true,
        "IAM Action Last Accessed": true
      }
    },
    {
      "Name": "DescribeEntitlements",
      "Annotations": {
        "Properties": {
          "IsList": true,
          "IsPermissionManagement": false,
          "IsTaggingOnly": false,
          "IsWrite": false
        }
      },
      "Resources": [
        {
          "Name": "stack"
        }
      ],
      "SupportedBy": {
        "IAM Access Analyzer Policy Generation": true,
        "IAM Action Last Accessed": true
      }
    },
    {
      "Name": "DescribeFleets",
      "Annotations": {
        "Properties": {
          "IsList": true,
          "IsPermissionManagement": false,
          "IsTaggingOnly": false,
          "IsWrite": false
        }
      },
      "SupportedBy": {
        "IAM Access Analyzer Policy Generation": true,
        "IAM Action Last Accessed": true
      }
    },
    {
      "Name": "DescribeImageBuilders",
      "Annotations": {
        "Properties": {
          "IsList": true,
          "IsPermissionManagement": false,
          "IsTaggingOnly": false,
          "IsWrite": false
        }
      },
      "SupportedBy": {
        "IAM Access Analyzer Policy Generation": true,
        "IAM Action Last Accessed": true
      }
    },
    {
      "Name": "DescribeImagePermissions",
      "Annotations": {
        "Properties": {
          "IsList": false,
          "IsPermissionManagement": false,
          "IsTaggingOnly": false,
          "IsWrite": false
        }
      },
      "Resources": [
        {
          "Name": "image"
        }
      ],
      "SupportedBy": {
        "IAM Access Analyzer Policy Generation": true,
        "IAM Action Last Accessed": true
      }
    },
    {
      "Name": "DescribeImages",
      "Annotations": {
        "Properties": {
          "IsList": true,
          "IsPermissionManagement": false,
          "IsTaggingOnly": false,
          "IsWrite": false
        }
      },
      "SupportedBy": {
        "IAM Access Analyzer Policy Generation": true,
        "IAM Action Last Accessed": true
      }
    },
    {
      "Name": "DescribeSessions",
      "Annotations": {
        "Properties": {
          "IsList": true,
          "IsPermissionManagement": false,
          "IsTaggingOnly": false,
          "IsWrite": false
        }
      },
      "Resources": [
        {
          "Name": "fleet"
        },
        {
          "Name": "stack"
        }
      ],
      "SupportedBy": {
        "IAM Access Analyzer Policy Generation": true,
        "IAM Action Last Accessed": true
      }
    },
    {
      "Name": "DescribeStacks",
      "Annotations": {
        "Properties": {
          "IsList": true,
          "IsPermissionManagement": false,
          "IsTaggingOnly": false,
          "IsWrite": false
        }
      },
      "SupportedBy": {
        "IAM Access Analyzer Policy Generation": true,
        "IAM Action Last Accessed": true
      }
    },
    {
      "Name": "DescribeThemeForStack",
      "Annotations": {
        "Properties": {
          "IsList": false,
          "IsPermissionManagement": false,
          "IsTaggingOnly": false,
          "IsWrite": false
        }
      },
      "Resources": [
        {
          "Name": "stack"
        }
      ],
      "SupportedBy": {
        "IAM Access Analyzer Policy Generation": true,
        "IAM Action Last Accessed": true
      }
    },
    {
      "Name": "DescribeUsageReportSubscriptions",
      "Annotations": {
        "Properties": {
          "IsList": true,
          "IsPermissionManagement": false,
          "IsTaggingOnly": false,
          "IsWrite": false
        }
      },
      "SupportedBy": {
        "IAM Access Analyzer Policy Generation": true,
        "IAM Action Last Accessed": true
      }
    },
    {
      "Name": "DescribeUserStackAssociations",
      "Annotations": {
        "Properties": {
          "IsList": true,
          "IsPermissionManagement": false,
          "IsTaggingOnly": false,
          "IsWrite": false
        }
      },
      "Resources": [
        {
          "Name": "stack"
        }
      ],
      "SupportedBy": {
        "IAM Access Analyzer Policy Generation": true,
        "IAM Action Last Accessed": true
      }
    },
    {
      "Name": "DescribeUsers",
      "Annotations": {
        "Properties": {
          "IsList": true,
          "IsPermissionManagement": false,
          "IsTaggingOnly": false,
          "IsWrite": false
        }
      },
      "SupportedBy": {
        "IAM Access Analyzer Policy Generation": true,
        "IAM Action Last Accessed": true
      }
    },
    {
      "Name": "DisableUser",
      "Annotations": {
        "Properties": {
          "IsList": false,
          "IsPermissionManagement": false,
          "IsTaggingOnly": false,
          "IsWrite": true
        }
      },
      "SupportedBy": {
        "IAM Access Analyzer Policy Generation": true,
        "IAM Action Last Accessed": true
      }
    },
    {
      "Name": "DisassociateAppBlockBuilderAppBlock",
      "ActionConditionKeys": [
        "aws:ResourceTag/${TagKey}"
      ],
      "Annotations": {
        "Properties": {
          "IsList": false,
          "IsPermissionManagement": false,
          "IsTaggingOnly": false,
          "IsWrite": true
        }
      },
      "Resources": [
        {
          "Name": "app-block"
        },
        {
          "Name": "app-block-builder"
        }
      ],
      "SupportedBy": {
        "IAM Access Analyzer Policy Generation": true,
        "IAM Action Last Accessed": true
      }
    },
    {
      "Name": "DisassociateApplicationFleet",
      "ActionConditionKeys": [
        "aws:ResourceTag/${TagKey}"
      ],
      "Annotations": {
        "Properties": {
          "IsList": false,
          "IsPermissionManagement": false,
          "IsTaggingOnly": false,
          "IsWrite": true
        }
      },
      "Resources": [
        {
          "Name": "application"
        },
        {
          "Name": "fleet"
        }
      ],
      "SupportedBy": {
        "IAM Access Analyzer Policy Generation": true,
        "IAM Action Last Accessed": true
      }
    },
    {
      "Name": "DisassociateApplicationFromEntitlement",
      "Annotations": {
        "Properties": {
          "IsList": false,
          "IsPermissionManagement": false,
          "IsTaggingOnly": false,
          "IsWrite": true
        }
      },
      "Resources": [
        {
          "Name": "stack"
        }
      ],
      "SupportedBy": {
        "IAM Access Analyzer Policy Generation": true,
        "IAM Action Last Accessed": true
      }
    },
    {
      "Name": "DisassociateFleet",
      "ActionConditionKeys": [
        "aws:ResourceTag/${TagKey}"
      ],
      "Annotations": {
        "Properties": {
          "IsList": false,
          "IsPermissionManagement": false,
          "IsTaggingOnly": false,
          "IsWrite": true
        }
      },
      "Resources": [
        {
          "Name": "fleet"
        },
        {
          "Name": "stack"
        }
      ],
      "SupportedBy": {
        "IAM Access Analyzer Policy Generation": true,
        "IAM Action Last Accessed": true
      }
    },
    {
      "Name": "EnableUser",
      "Annotations": {
        "Properties": {
          "IsList": false,
          "IsPermissionManagement": false,
          "IsTaggingOnly": false,
          "IsWrite": true
        }
      },
      "SupportedBy": {
        "IAM Access Analyzer Policy Generation": true,
        "IAM Action Last Accessed": true
      }
    },
    {
      "Name": "ExpireSession",
      "Annotations": {
        "Properties": {
          "IsList": false,
          "IsPermissionManagement": false,
          "IsTaggingOnly": false,
          "IsWrite": true
        }
      },
      "SupportedBy": {
        "IAM Access Analyzer Policy Generation": true,
        "IAM Action Last Accessed": true
      }
    },
    {
      "Name": "ListAssociatedFleets",
      "Annotations": {
        "Properties": {
          "IsList": false,
          "IsPermissionManagement": false,
          "IsTaggingOnly": false,
          "IsWrite": false
        }
      },
      "Resources": [
        {
          "Name": "stack"
        }
      ],
      "SupportedBy": {
        "IAM Access Analyzer Policy Generation": true,
        "IAM Action Last Accessed": true
      }
    },
    {
      "Name": "ListAssociatedStacks",
      "Annotations": {
        "Properties": {
          "IsList": false,
          "IsPermissionManagement": false,
          "IsTaggingOnly": false,
          "IsWrite": false
        }
      },
      "Resources": [
        {
          "Name": "fleet"
        }
      ],
      "SupportedBy": {
        "IAM Access Analyzer Policy Generation": true,
        "IAM Action Last Accessed": true
      }
    },
    {
      "Name": "ListEntitledApplications",
      "Annotations": {
        "Properties": {
          "IsList": true,
          "IsPermissionManagement": false,
          "IsTaggingOnly": false,
          "IsWrite": false
        }
      },
      "Resources": [
        {
          "Name": "stack"
        }
      ],
      "SupportedBy": {
        "IAM Access Analyzer Policy Generation": true,
        "IAM Action Last Accessed": true
      }
    },
    {
      "Name": "ListTagsForResource",
      "Annotations": {
        "Properties": {
          "IsList": false,
          "IsPermissionManagement": false,
          "IsTaggingOnly": false,
          "IsWrite": false
        }
      },
      "SupportedBy": {
        "IAM Access Analyzer Policy Generation": true,
        "IAM Action Last Accessed": false
      }
    },
    {
      "Name": "StartAppBlockBuilder",
      "ActionConditionKeys": [
        "aws:ResourceTag/${TagKey}"
      ],
      "Annotations": {
        "Properties": {
          "IsList": false,
          "IsPermissionManagement": false,
          "IsTaggingOnly": false,
          "IsWrite": true
        }
      },
      "Resources": [
        {
          "Name": "app-block-builder"
        }
      ],
      "SupportedBy": {
        "IAM Access Analyzer Policy Generation": true,
        "IAM Action Last Accessed": true
      }
    },
    {
      "Name": "StartFleet",
      "ActionConditionKeys": [
        "aws:ResourceTag/${TagKey}"
      ],
      "Annotations": {
        "Properties": {
          "IsList": false,
          "IsPermissionManagement": false,
          "IsTaggingOnly": false,
          "IsWrite": true
        }
      },
      "Resources": [
        {
          "Name": "fleet"
        }
      ],
      "SupportedBy": {
        "IAM Access Analyzer Policy Generation": true,
        "IAM Action Last Accessed": true
      }
    },
    {
      "Name": "StartImageBuilder",
      "ActionConditionKeys": [
        "aws:ResourceTag/${TagKey}"
      ],
      "Annotations": {
        "Properties": {
          "IsList": false,
          "IsPermissionManagement": false,
          "IsTaggingOnly": false,
          "IsWrite": true
        }
      },
      "Resources": [
        {
          "Name": "image-builder"
        }
      ],
      "SupportedBy": {
        "IAM Access Analyzer Policy Generation": true,
        "IAM Action Last Accessed": true
      }
    },
    {
      "Name": "StopAppBlockBuilder",
      "ActionConditionKeys": [
        "aws:ResourceTag/${TagKey}"
      ],
      "Annotations": {
        "Properties": {
          "IsList": false,
          "IsPermissionManagement": false,
          "IsTaggingOnly": false,
          "IsWrite": true
        }
      },
      "Resources": [
        {
          "Name": "app-block-builder"
        }
      ],
      "SupportedBy": {
        "IAM Access Analyzer Policy Generation": true,
        "IAM Action Last Accessed": true
      }
    },
    {
      "Name": "StopFleet",
      "ActionConditionKeys": [
        "aws:ResourceTag/${TagKey}"
      ],
      "Annotations": {
        "Properties": {
          "IsList": false,
          "IsPermissionManagement": false,
          "IsTaggingOnly": false,
          "IsWrite": true
        }
      },
      "Resources": [
        {
          "Name": "fleet"
        }
      ],
      "SupportedBy": {
        "IAM Access Analyzer Policy Generation": true,
        "IAM Action Last Accessed": true
      }
    },
    {
      "Name": "StopImageBuilder",
      "ActionConditionKeys": [
        "aws:ResourceTag/${TagKey}"
      ],
      "Annotations": {
        "Properties": {
          "IsList": false,
          "IsPermissionManagement": false,
          "IsTaggingOnly": false,
          "IsWrite": true
        }
      },
      "Resources": [
        {
          "Name": "image-builder"
        }
      ],
      "SupportedBy": {
        "IAM Access Analyzer Policy Generation": true,
        "IAM Action Last Accessed": true
      }
    },
    {
      "Name": "Stream",
      "ActionConditionKeys": [
        "appstream:userId"
      ],
      "Annotations": {
        "Properties": {
          "IsList": false,
          "IsPermissionManagement": false,
          "IsTaggingOnly": false,
          "IsWrite": true
        }
      },
      "Resources": [
        {
          "Name": "stack"
        }
      ],
      "SupportedBy": {
        "IAM Access Analyzer Policy Generation": false,
        "IAM Action Last Accessed": false
      }
    },
    {
      "Name": "TagResource",
      "ActionConditionKeys": [
        "aws:RequestTag/${TagKey}",
        "aws:ResourceTag/${TagKey}",
        "aws:TagKeys"
      ],
      "Annotations": {
        "Properties": {
          "IsList": false,
          "IsPermissionManagement": false,
          "IsTaggingOnly": true,
          "IsWrite": true
        }
      },
      "Resources": [
        {
          "Name": "app-block"
        },
        {
          "Name": "app-block-builder"
        },
        {
          "Name": "application"
        },
        {
          "Name": "fleet"
        },
        {
          "Name": "image"
        },
        {
          "Name": "image-builder"
        },
        {
          "Name": "stack"
        }
      ],
      "SupportedBy": {
        "IAM Access Analyzer Policy Generation": true,
        "IAM Action Last Accessed": false
      }
    },
    {
      "Name": "UntagResource",
      "ActionConditionKeys": [
        "aws:TagKeys"
      ],
      "Annotations": {
        "Properties": {
          "IsList": false,
          "IsPermissionManagement": false,
          "IsTaggingOnly": true,
          "IsWrite": true
        }
      },
      "Resources": [
        {
          "Name": "app-block"
        },
        {
          "Name": "app-block-builder"
        },
        {
          "Name": "application"
        },
        {
          "Name": "fleet"
        },
        {
          "Name": "image"
        },
        {
          "Name": "image-builder"
        },
        {
          "Name": "stack"
        }
      ],
      "SupportedBy": {
        "IAM Access Analyzer Policy Generation": true,
        "IAM Action Last Accessed": false
      }
    },
    {
      "Name": "UpdateAppBlockBuilder",
      "ActionConditionKeys": [
        "aws:ResourceTag/${TagKey}"
      ],
      "Annotations": {
        "Properties": {
          "IsList": false,
          "IsPermissionManagement": false,
          "IsTaggingOnly": false,
          "IsWrite": true
        }
      },
      "Resources": [
        {
          "Name": "app-block-builder"
        }
      ],
      "SupportedBy": {
        "IAM Access Analyzer Policy Generation": true,
        "IAM Action Last Accessed": true
      }
    },
    {
      "Name": "UpdateApplication",
      "ActionConditionKeys": [
        "aws:ResourceTag/${TagKey}"
      ],
      "Annotations": {
        "Properties": {
          "IsList": false,
          "IsPermissionManagement": false,
          "IsTaggingOnly": false,
          "IsWrite": true
        }
      },
      "Resources": [
        {
          "Name": "app-block"
        },
        {
          "Name": "application"
        }
      ],
      "SupportedBy": {
        "IAM Access Analyzer Policy Generation": true,
        "IAM Action Last Accessed": true
      }
    },
    {
      "Name": "UpdateDirectoryConfig",
      "Annotations": {
        "Properties": {
          "IsList": false,
          "IsPermissionManagement": false,
          "IsTaggingOnly": false,
          "IsWrite": true
        }
      },
      "SupportedBy": {
        "IAM Access Analyzer Policy Generation": true,
        "IAM Action Last Accessed": true
      }
    },
    {
      "Name": "UpdateEntitlement",
      "Annotations": {
        "Properties": {
          "IsList": false,
          "IsPermissionManagement": false,
          "IsTaggingOnly": false,
          "IsWrite": true
        }
      },
      "Resources": [
        {
          "Name": "stack"
        }
      ],
      "SupportedBy": {
        "IAM Access Analyzer Policy Generation": true,
        "IAM Action Last Accessed": true
      }
    },
    {
      "Name": "UpdateFleet",
      "ActionConditionKeys": [
        "aws:ResourceTag/${TagKey}"
      ],
      "Annotations": {
        "Properties": {
          "IsList": false,
          "IsPermissionManagement": false,
          "IsTaggingOnly": false,
          "IsWrite": true
        }
      },
      "Resources": [
        {
          "Name": "fleet"
        },
        {
          "Name": "image"
        }
      ],
      "SupportedBy": {
        "IAM Access Analyzer Policy Generation": true,
        "IAM Action Last Accessed": true
      }
    },
    {
      "Name": "UpdateImagePermissions",
      "ActionConditionKeys": [
        "aws:ResourceTag/${TagKey}"
      ],
      "Annotations": {
        "Properties": {
          "IsList": false,
          "IsPermissionManagement": false,
          "IsTaggingOnly": false,
          "IsWrite": true
        }
      },
      "Resources": [
        {
          "Name": "image"
        }
      ],
      "SupportedBy": {
        "IAM Access Analyzer Policy Generation": true,
        "IAM Action Last Accessed": true
      }
    },
    {
      "Name": "UpdateStack",
      "ActionConditionKeys": [
        "aws:ResourceTag/${TagKey}"
      ],
      "Annotations": {
        "Properties": {
          "IsList": false,
          "IsPermissionManagement": false,
          "IsTaggingOnly": false,
          "IsWrite": true
        }
      },
      "Resources": [
        {
          "Name": "stack"
        }
      ],
      "SupportedBy": {
        "IAM Access Analyzer Policy Generation": true,
        "IAM Action Last Accessed": true
      }
    },
    {
      "Name": "UpdateThemeForStack",
      "Annotations": {
        "Properties": {
          "IsList": false,
          "IsPermissionManagement": false,
          "IsTaggingOnly": false,
          "IsWrite": true
        }
      },
      "Resources": [
        {
          "Name": "stack"
        }
      ],
      "SupportedBy": {
        "IAM Access Analyzer Policy Generation": true,
        "IAM Action Last Accessed": true
      }
    }
  ],
  "ConditionKeys": [
    {
      "Name": "appstream:userId",
      "Types": [
        "String"
      ]
    },
    {
      "Name": "aws:RequestTag/${TagKey}",
      "Types": [
        "String"
      ]
    },
    {
      "Name": "aws:ResourceTag/${TagKey}",
      "Types": [
        "String"
      ]
    },
    {
      "Name": "aws:TagKeys",
      "Types": [
        "ArrayOfString"
      ]
    }
  ],
  "Resources": [
    {
      "Name": "app-block",
      "ARNFormats": [
        "arn:${Partition}:appstream:${Region}:${Account}:app-block/${AppBlockName}"
      ],
      "ConditionKeys": [
        "aws:ResourceTag/${TagKey}"
      ]
    },
    {
      "Name": "app-block-builder",
      "ARNFormats": [
        "arn:${Partition}:appstream:${Region}:${Account}:app-block-builder/${AppBlockBuilderName}"
      ],
      "ConditionKeys": [
        "aws:ResourceTag/${TagKey}"
      ]
    },
    {
      "Name": "application",
      "ARNFormats": [
        "arn:${Partition}:appstream:${Region}:${Account}:application/${ApplicationName}"
      ],
      "ConditionKeys": [
        "aws:ResourceTag/${TagKey}"
      ]
    },
    {
      "Name": "fleet",
      "ARNFormats": [
        "arn:${Partition}:appstream:${Region}:${Account}:fleet/${FleetName}"
      ],
      "ConditionKeys": [
        "aws:ResourceTag/${TagKey}"
      ]
    },
    {
      "Name": "image",
      "ARNFormats": [
        "arn:${Partition}:appstream:${Region}:${Account}:image/${ImageName}"
      ],
      "ConditionKeys": [
        "aws:ResourceTag/${TagKey}"
      ]
    },
    {
      "Name": "image-builder",
      "ARNFormats": [
        "arn:${Partition}:appstream:${Region}:${Account}:image-builder/${ImageBuilderName}"
      ],
      "ConditionKeys": [
        "aws:ResourceTag/${TagKey}"
      ]
    },
    {
      "Name": "stack",
      "ARNFormats": [
        "arn:${Partition}:appstream:${Region}:${Account}:stack/${StackName}"
      ],
      "ConditionKeys": [
        "aws:ResourceTag/${TagKey}"
      ]
    }
  ],
  "Version": "v1.3"
}