{
  "Name": "mediapackagev2",
  "Actions": [
    {
      "Name": "CancelHarvestJob",
      "Annotations": {
        "Properties": {
          "IsList": false,
          "IsPermissionManagement": false,
          "IsTaggingOnly": false,
          "IsWrite": true
        }
      },
      "Resources": [
        {
          "Name": "Channel"
        },
        {
          "Name": "ChannelGroup"
        },
        {
          "Name": "HarvestJob"
        },
        {
          "Name": "OriginEndpoint"
        }
      ],
      "SupportedBy": {
        "IAM Access Analyzer Policy Generation": false,
        "IAM Action Last Accessed": false
      }
    },
    {
      "Name": "CreateChannel",
      "ActionConditionKeys": [
        "aws:RequestTag/${TagKey}",
        "aws:TagKeys"
      ],
      "Annotations": {
        "Properties": {
          "IsList": false,
          "IsPermissionManagement": false,
          "IsTaggingOnly": false,
          "IsWrite": true
        }
      },
      "Resources": [
        {
          "Name": "Channel"
        },
        {
          "Name": "ChannelGroup"
        }
      ],
      "SupportedBy": {
        "IAM Access Analyzer Policy Generation": false,
        "IAM Action Last Accessed": false
      }
    },
    {
      "Name": "CreateChannelGroup",
      "ActionConditionKeys": [
        "aws:RequestTag/${TagKey}",
        "aws:TagKeys"
      ],
      "Annotations": {
        "Properties": {
          "IsList": false,
          "IsPermissionManagement": false,
          "IsTaggingOnly": false,
          "IsWrite": true
        }
      },
      "Resources": [
        {
          "Name": "ChannelGroup"
        }
      ],
      "SupportedBy": {
        "IAM Access Analyzer Policy Generation": false,
        "IAM Action Last Accessed": false
      }
    },
    {
      "Name": "CreateHarvestJob",
      "ActionConditionKeys": [
        "aws:RequestTag/${TagKey}",
        "aws:TagKeys"
      ],
      "Annotations": {
        "Properties": {
          "IsList": false,
          "IsPermissionManagement": false,
          "IsTaggingOnly": false,
          "IsWrite": true
        }
      },
      "Resources": [
        {
          "Name": "Channel"
        },
        {
          "Name": "ChannelGroup"
        },
        {
          "Name": "HarvestJob"
        },
        {
          "Name": "OriginEndpoint"
        }
      ],
      "SupportedBy": {
        "IAM Access Analyzer Policy Generation": false,
        "IAM Action Last Accessed": false
      }
    },
    {
      "Name": "CreateOriginEndpoint",
      "ActionConditionKeys": [
        "aws:RequestTag/${TagKey}",
        "aws:TagKeys"
      ],
      "Annotations": {
        "Properties": {
          "IsList": false,
          "IsPermissionManagement": false,
          "IsTaggingOnly": false,
          "IsWrite": true
        }
      },
      "Resources": [
        {
          "Name": "Channel"
        },
        {
          "Name": "ChannelGroup"
        },
        {
          "Name": "OriginEndpoint"
        }
      ],
      "SupportedBy": {
        "IAM Access Analyzer Policy Generation": false,
        "IAM Action Last Accessed": false
      }
    },
    {
      "Name": "DeleteChannel",
      "Annotations": {
        "Properties": {
          "IsList": false,
          "IsPermissionManagement": false,
          "IsTaggingOnly": false,
          "IsWrite": true
        }
      },
      "Resources": [
        {
          "Name": "Channel"
        },
        {
          "Name": "ChannelGroup"
        }
      ],
      "SupportedBy": {
        "IAM Access Analyzer Policy Generation": false,
        "IAM Action Last Accessed": false
      }
    },
    {
      "Name": "DeleteChannelGroup",
      "Annotations": {
        "Properties": {
          "IsList": false,
          "IsPermissionManagement": false,
          "IsTaggingOnly": false,
          "IsWrite": true
        }
      },
      "Resources": [
        {
          "Name": "ChannelGroup"
        }
      ],
      "SupportedBy": {
        "IAM Access Analyzer Policy Generation": false,
        "IAM Action Last Accessed": false
      }
    },
    {
      "Name": "DeleteChannelPolicy",
      "Annotations": {
        "Properties": {
          "IsList": false,
          "IsPermissionManagement": false,
          "IsTaggingOnly": false,
          "IsWrite": true
        }
      },
      "Resources": [
        {
          "Name": "Channel"
        },
        {
          "Name": "ChannelGroup"
        },
        {
          "Name": "ChannelPolicy"
        }
      ],
      "SupportedBy": {
        "IAM Access Analyzer Policy Generation": false,
        "IAM Action Last Accessed": false
      }
    },
    {
      "Name": "DeleteOriginEndpoint",
      "Annotations": {
        "Properties": {
          "IsList": false,
          "IsPermissionManagement": false,
          "IsTaggingOnly": false,
          "IsWrite": true
        }
      },
      "Resources": [
        {
          "Name": "Channel"
        },
        {
          "Name": "ChannelGroup"
        },
        {
          "Name": "OriginEndpoint"
        }
      ],
      "SupportedBy": {
        "IAM Access Analyzer Policy Generation": false,
        "IAM Action Last Accessed": false
      }
    },
    {
      "Name": "DeleteOriginEndpointPolicy",
      "Annotations": {
        "Properties": {
          "IsList": false,
          "IsPermissionManagement": false,
          "IsTaggingOnly": false,
          "IsWrite": true
        }
      },
      "Resources": [
        {
          "Name": "Channel"
        },
        {
          "Name": "ChannelGroup"
        },
        {
          "Name": "OriginEndpoint"
        },
        {
          "Name": "OriginEndpointPolicy"
        }
      ],
      "SupportedBy": {
        "IAM Access Analyzer Policy Generation": false,
        "IAM Action Last Accessed": false
      }
    },
    {
      "Name": "GetChannel",
      "Annotations": {
        "Properties": {
          "IsList": false,
          "IsPermissionManagement": false,
          "IsTaggingOnly": false,
          "IsWrite": false
        }
      },
      "Resources": [
        {
          "Name": "Channel"
        },
        {
          "Name": "ChannelGroup"
        }
      ],
      "SupportedBy": {
        "IAM Access Analyzer Policy Generation": false,
        "IAM Action Last Accessed": false
      }
    },
    {
      "Name": "GetChannelGroup",
      "Annotations": {
        "Properties": {
          "IsList": false,
          "IsPermissionManagement": false,
          "IsTaggingOnly": false,
          "IsWrite": false
        }
      },
      "Resources": [
        {
          "Name": "ChannelGroup"
        }
      ],
      "SupportedBy": {
        "IAM Access Analyzer Policy Generation": false,
        "IAM Action Last Accessed": false
      }
    },
    {
      "Name": "GetChannelPolicy",
      "Annotations": {
        "Properties": {
          "IsList": false,
          "IsPermissionManagement": false,
          "IsTaggingOnly": false,
          "IsWrite": false
        }
      },
      "Resources": [
        {
          "Name": "Channel"
        },
        {
          "Name": "ChannelGroup"
        },
        {
          "Name": "ChannelPolicy"
        }
      ],
      "SupportedBy": {
        "IAM Access Analyzer Policy Generation": false,
        "IAM Action Last Accessed": false
      }
    },
    {
      "Name": "GetHarvestJob",
      "Annotations": {
        "Properties": {
          "IsList": false,
          "IsPermissionManagement": false,
          "IsTaggingOnly": false,
          "IsWrite": false
        }
      },
      "Resources": [
        {
          "Name": "Channel"
        },
        {
          "Name": "ChannelGroup"
        },
        {
          "Name": "HarvestJob"
        },
        {
          "Name": "OriginEndpoint"
        }
      ],
      "SupportedBy": {
        "IAM Access Analyzer Policy Generation": false,
        "IAM Action Last Accessed": false
      }
    },
    {
      "Name": "GetHeadObject",
      "Annotations": {
        "Properties": {
          "IsList": false,
          "IsPermissionManagement": false,
          "IsTaggingOnly": false,
          "IsWrite": false
        }
      },
      "Resources": [
        {
          "Name": "OriginEndpoint"
        }
      ],
      "SupportedBy": {
        "IAM Access Analyzer Policy Generation": false,
        "IAM Action Last Accessed": false
      }
    },
    {
      "Name": "GetObject",
      "Annotations": {
        "Properties": {
          "IsList": false,
          "IsPermissionManagement": false,
          "IsTaggingOnly": false,
          "IsWrite": false
        }
      },
      "Resources": [
        {
          "Name": "OriginEndpoint"
        }
      ],
      "SupportedBy": {
        "IAM Access Analyzer Policy Generation": false,
        "IAM Action Last Accessed": false
      }
    },
    {
      "Name": "GetOriginEndpoint",
      "Annotations": {
        "Properties": {
          "IsList": false,
          "IsPermissionManagement": false,
          "IsTaggingOnly": false,
          "IsWrite": false
        }
      },
      "Resources": [
        {
          "Name": "Channel"
        },
        {
          "Name": "ChannelGroup"
        },
        {
          "Name": "OriginEndpoint"
        }
      ],
      "SupportedBy": {
        "IAM Access Analyzer Policy Generation": false,
        "IAM Action Last Accessed": false
      }
    },
    {
      "Name": "GetOriginEndpointPolicy",
      "Annotations": {
        "Properties": {
          "IsList": false,
          "IsPermissionManagement": false,
          "IsTaggingOnly": false,
          "IsWrite": false
        }
      },
      "Resources": [
        {
          "Name": "Channel"
        },
        {
          "Name": "ChannelGroup"
        },
        {
          "Name": "OriginEndpoint"
        },
        {
          "Name": "OriginEndpointPolicy"
        }
      ],
      "SupportedBy": {
        "IAM Access Analyzer Policy Generation": false,
        "IAM Action Last Accessed": false
      }
    },
    {
      "Name": "HarvestObject",
      "Annotations": {
        "Properties": {
          "IsList": false,
          "IsPermissionManagement": false,
          "IsTaggingOnly": false,
          "IsWrite": false
        }
      },
      "Resources": [
        {
          "Name": "OriginEndpoint"
        }
      ],
      "SupportedBy": {
        "IAM Access Analyzer Policy Generation": false,
        "IAM Action Last Accessed": false
      }
    },
    {
      "Name": "ListChannelGroups",
      "Annotations": {
        "Properties": {
          "IsList": true,
          "IsPermissionManagement": false,
          "IsTaggingOnly": false,
          "IsWrite": false
        }
      },
      "SupportedBy": {
        "IAM Access Analyzer Policy Generation": false,
        "IAM Action Last Accessed": false
      }
    },
    {
      "Name": "ListChannels",
      "Annotations": {
        "Properties": {
          "IsList": true,
          "IsPermissionManagement": false,
          "IsTaggingOnly": false,
          "IsWrite": false
        }
      },
      "Resources": [
        {
          "Name": "ChannelGroup"
        }
      ],
      "SupportedBy": {
        "IAM Access Analyzer Policy Generation": false,
        "IAM Action Last Accessed": false
      }
    },
    {
      "Name": "ListHarvestJobs",
      "Annotations": {
        "Properties": {
          "IsList": true,
          "IsPermissionManagement": false,
          "IsTaggingOnly": false,
          "IsWrite": false
        }
      },
      "Resources": [
        {
          "Name": "ChannelGroup"
        }
      ],
      "SupportedBy": {
        "IAM Access Analyzer Policy Generation": false,
        "IAM Action Last Accessed": false
      }
    },
    {
      "Name": "ListOriginEndpoints",
      "Annotations": {
        "Properties": {
          "IsList": true,
          "IsPermissionManagement": false,
          "IsTaggingOnly": false,
          "IsWrite": false
        }
      },
      "Resources": [
        {
          "Name": "Channel"
        },
        {
          "Name": "ChannelGroup"
        }
      ],
      "SupportedBy": {
        "IAM Access Analyzer Policy Generation": false,
        "IAM Action Last Accessed": false
      }
    },
    {
      "Name": "ListTagsForResource",
      "Annotations": {
        "Properties": {
          "IsList": false,
          "IsPermissionManagement": false,
          "IsTaggingOnly": false,
          "IsWrite": false
        }
      },
      "Resources": [
        {
          "Name": "Channel"
        },
        {
          "Name": "ChannelGroup"
        },
        {
          "Name": "HarvestJob"
        },
        {
          "Name": "OriginEndpoint"
        }
      ],
      "SupportedBy": {
        "IAM Access Analyzer Policy Generation": false,
        "IAM Action Last Accessed": false
      }
    },
    {
      "Name": "PutChannelPolicy",
      "Annotations": {
        "Properties": {
          "IsList": false,
          "IsPermissionManagement": false,
          "IsTaggingOnly": false,
          "IsWrite": true
        }
      },
      "Resources": [
        {
          "Name": "Channel"
        },
        {
          "Name": "ChannelGroup"
        },
        {
          "Name": "ChannelPolicy"
        }
      ],
      "SupportedBy": {
        "IAM Access Analyzer Policy Generation": false,
        "IAM Action Last Accessed": false
      }
    },
    {
      "Name": "PutObject",
      "Annotations": {
        "Properties": {
          "IsList": false,
          "IsPermissionManagement": false,
          "IsTaggingOnly": false,
          "IsWrite": true
        }
      },
      "Resources": [
        {
          "Name": "Channel"
        }
      ],
      "SupportedBy": {
        "IAM Access Analyzer Policy Generation": false,
        "IAM Action Last Accessed": false
      }
    },
    {
      "Name": "PutOriginEndpointPolicy",
      "Annotations": {
        "Properties": {
          "IsList": false,
          "IsPermissionManagement": false,
          "IsTaggingOnly": false,
          "IsWrite": true
        }
      },
      "Resources": [
        {
          "Name": "Channel"
        },
        {
          "Name": "ChannelGroup"
        },
        {
          "Name": "OriginEndpoint"
        },
        {
          "Name": "OriginEndpointPolicy"
        }
      ],
      "SupportedBy": {
        "IAM Access Analyzer Policy Generation": false,
        "IAM Action Last Accessed": false
      }
    },
    {
      "Name": "ResetChannelState",
      "Annotations": {
        "Properties": {
          "IsList": false,
          "IsPermissionManagement": false,
          "IsTaggingOnly": false,
          "IsWrite": true
        }
      },
      "Resources": [
        {
          "Name": "Channel"
        },
        {
          "Name": "ChannelGroup"
        }
      ],
      "SupportedBy": {
        "IAM Access Analyzer Policy Generation": false,
        "IAM Action Last Accessed": false
      }
    },
    {
      "Name": "ResetOriginEndpointState",
      "Annotations": {
        "Properties": {
          "IsList": false,
          "IsPermissionManagement": false,
          "IsTaggingOnly": false,
          "IsWrite": true
        }
      },
      "Resources": [
        {
          "Name": "Channel"
        },
        {
          "Name": "ChannelGroup"
        },
        {
          "Name": "OriginEndpoint"
        }
      ],
      "SupportedBy": {
        "IAM Access Analyzer Policy Generation": false,
        "IAM Action Last Accessed": false
      }
    },
    {
      "Name": "TagResource",
      "ActionConditionKeys": [
        "aws:RequestTag/${TagKey}",
        "aws:TagKeys"
      ],
      "Annotations": {
        "Properties": {
          "IsList": false,
          "IsPermissionManagement": false,
          "IsTaggingOnly": true,
          "IsWrite": true
        }
      },
      "Resources": [
        {
          "Name": "Channel"
        },
        {
          "Name": "ChannelGroup"
        },
        {
          "Name": "HarvestJob"
        },
        {
          "Name": "OriginEndpoint"
        }
      ],
      "SupportedBy": {
        "IAM Access Analyzer Policy Generation": false,
        "IAM Action Last Accessed": false
      }
    },
    {
      "Name": "UntagResource",
      "ActionConditionKeys": [
        "aws:TagKeys"
      ],
      "Annotations": {
        "Properties": {
          "IsList": false,
          "IsPermissionManagement": false,
          "IsTaggingOnly": true,
          "IsWrite": true
        }
      },
      "Resources": [
        {
          "Name": "Channel"
        },
        {
          "Name": "ChannelGroup"
        },
        {
          "Name": "HarvestJob"
        },
        {
          "Name": "OriginEndpoint"
        }
      ],
      "SupportedBy": {
        "IAM Access Analyzer Policy Generation": false,
        "IAM Action Last Accessed": false
      }
    },
    {
      "Name": "UpdateChannel",
      "Annotations": {
        "Properties": {
          "IsList": false,
          "IsPermissionManagement": false,
          "IsTaggingOnly": false,
          "IsWrite": true
        }
      },
      "Resources": [
        {
          "Name": "Channel"
        },
        {
          "Name": "ChannelGroup"
        }
      ],
      "SupportedBy": {
        "IAM Access Analyzer Policy Generation": false,
        "IAM Action Last Accessed": false
      }
    },
    {
      "Name": "UpdateChannelGroup",
      "Annotations": {
        "Properties": {
          "IsList": false,
          "IsPermissionManagement": false,
          "IsTaggingOnly": false,
          "IsWrite": true
        }
      },
      "Resources": [
        {
          "Name": "ChannelGroup"
        }
      ],
      "SupportedBy": {
        "IAM Access Analyzer Policy Generation": false,
        "IAM Action Last Accessed": false
      }
    },
    {
      "Name": "UpdateOriginEndpoint",
      "Annotations": {
        "Properties": {
          "IsList": false,
          "IsPermissionManagement": false,
          "IsTaggingOnly": false,
          "IsWrite": true
        }
      },
      "Resources": [
        {
          "Name": "Channel"
        },
        {
          "Name": "ChannelGroup"
        },
        {
          "Name": "OriginEndpoint"
        }
      ],
      "SupportedBy": {
        "IAM Access Analyzer Policy Generation": false,
        "IAM Action Last Accessed": false
      }
    }
  ],
  "ConditionKeys": [
    {
      "Name": "aws:RequestTag/${TagKey}",
      "Types": [
        "String"
      ]
    },
    {
      "Name": "aws:ResourceTag/${TagKey}",
      "Types": [
        "String"
      ]
    },
    {
      "Name": "aws:TagKeys",
      "Types": [
        "ArrayOfString"
      ]
    }
  ],
  "Resources": [
    {
      "Name": "Channel",
      "ARNFormats": [
        "arn:${Partition}:mediapackagev2:${Region}:${Account}:channelGroup/${ChannelGroupName}/channel/${ChannelName}"
      ],
      "ConditionKeys": [
        "aws:ResourceTag/${TagKey}"
      ]
    },
    {
      "Name": "ChannelGroup",
      "ARNFormats": [
        "arn:${Partition}:mediapackagev2:${Region}:${Account}:channelGroup/${ChannelGroupName}"
      ],
      "ConditionKeys": [
        "aws:ResourceTag/${TagKey}"
      ]
    },
    {
      "Name": "ChannelPolicy",
      "ARNFormats": [
        "arn:${Partition}:mediapackagev2:${Region}:${Account}:channelGroup/${ChannelGroupName}/channel/${ChannelName}"
      ]
    },
    {
      "Name": "HarvestJob",
      "ARNFormats": [
        "arn:${Partition}:mediapackagev2:${Region}:${Account}:channelGroup/${ChannelGroupName}/channel/${ChannelName}/originEndpoint/${OriginEndpointName}/harvestJob/${HarvestJobName}"
      ],
      "ConditionKeys": [
        "aws:ResourceTag/${TagKey}"
      ]
    },
    {
      "Name": "OriginEndpoint",
      "ARNFormats": [
        "arn:${Partition}:mediapackagev2:${Region}:${Account}:channelGroup/${ChannelGroupName}/channel/${ChannelName}/originEndpoint/${OriginEndpointName}"
      ],
      "ConditionKeys": [
        "aws:ResourceTag/${TagKey}"
      ]
    },
    {
      "Name": "OriginEndpointPolicy",
      "ARNFormats": [
        "arn:${Partition}:mediapackagev2:${Region}:${Account}:channelGroup/${ChannelGroupName}/channel/${ChannelName}/originEndpoint/${OriginEndpointName}"
      ]
    }
  ],
  "Version": "v1.3"
}