{
  "Name": "vpc-lattice",
  "Actions": [
    {
      "Name": "AssociateViaAWSService",
      "Annotations": {
        "Properties": {
          "IsList": false,
          "IsPermissionManagement": true,
          "IsTaggingOnly": false,
          "IsWrite": true
        }
      },
      "SupportedBy": {
        "IAM Access Analyzer Policy Generation": false,
        "IAM Action Last Accessed": false
      }
    },
    {
      "Name": "AssociateViaAWSService-EventsAndStates",
      "Annotations": {
        "Properties": {
          "IsList": false,
          "IsPermissionManagement": true,
          "IsTaggingOnly": false,
          "IsWrite": true
        }
      },
      "SupportedBy": {
        "IAM Access Analyzer Policy Generation": false,
        "IAM Action Last Accessed": false
      }
    },
    {
      "Name": "CreateAccessLogSubscription",
      "ActionConditionKeys": [
        "aws:RequestTag/${TagKey}",
        "aws:TagKeys"
      ],
      "Annotations": {
        "Properties": {
          "IsList": false,
          "IsPermissionManagement": false,
          "IsTaggingOnly": false,
          "IsWrite": true
        }
      },
      "Resources": [
        {
          "Name": "AccessLogSubscription"
        },
        {
          "Name": "ResourceConfiguration"
        },
        {
          "Name": "Service"
        },
        {
          "Name": "ServiceNetwork"
        }
      ],
      "SupportedBy": {
        "IAM Access Analyzer Policy Generation": true,
        "IAM Action Last Accessed": true
      }
    },
    {
      "Name": "CreateListener",
      "ActionConditionKeys": [
        "aws:RequestTag/${TagKey}",
        "aws:TagKeys",
        "vpc-lattice:Protocol",
        "vpc-lattice:TargetGroupArns"
      ],
      "Annotations": {
        "Properties": {
          "IsList": false,
          "IsPermissionManagement": false,
          "IsTaggingOnly": false,
          "IsWrite": true
        }
      },
      "Resources": [
        {
          "Name": "Listener"
        }
      ],
      "SupportedBy": {
        "IAM Access Analyzer Policy Generation": true,
        "IAM Action Last Accessed": true
      }
    },
    {
      "Name": "CreateResourceConfiguration",
      "ActionConditionKeys": [
        "aws:RequestTag/${TagKey}",
        "aws:TagKeys"
      ],
      "Annotations": {
        "Properties": {
          "IsList": false,
          "IsPermissionManagement": false,
          "IsTaggingOnly": false,
          "IsWrite": true
        }
      },
      "Resources": [
        {
          "Name": "ResourceConfiguration"
        },
        {
          "Name": "ResourceGateway"
        }
      ],
      "SupportedBy": {
        "IAM Access Analyzer Policy Generation": true,
        "IAM Action Last Accessed": true
      }
    },
    {
      "Name": "CreateResourceGateway",
      "ActionConditionKeys": [
        "aws:RequestTag/${TagKey}",
        "aws:TagKeys",
        "vpc-lattice:VpcId"
      ],
      "Annotations": {
        "Properties": {
          "IsList": false,
          "IsPermissionManagement": false,
          "IsTaggingOnly": false,
          "IsWrite": true
        }
      },
      "Resources": [
        {
          "Name": "ResourceGateway"
        }
      ],
      "SupportedBy": {
        "IAM Access Analyzer Policy Generation": true,
        "IAM Action Last Accessed": true
      }
    },
    {
      "Name": "CreateRule",
      "ActionConditionKeys": [
        "aws:RequestTag/${TagKey}",
        "aws:TagKeys",
        "vpc-lattice:TargetGroupArns"
      ],
      "Annotations": {
        "Properties": {
          "IsList": false,
          "IsPermissionManagement": false,
          "IsTaggingOnly": false,
          "IsWrite": true
        }
      },
      "Resources": [
        {
          "Name": "Rule"
        }
      ],
      "SupportedBy": {
        "IAM Access Analyzer Policy Generation": true,
        "IAM Action Last Accessed": true
      }
    },
    {
      "Name": "CreateService",
      "ActionConditionKeys": [
        "aws:RequestTag/${TagKey}",
        "aws:TagKeys",
        "vpc-lattice:AuthType"
      ],
      "Annotations": {
        "Properties": {
          "IsList": false,
          "IsPermissionManagement": false,
          "IsTaggingOnly": false,
          "IsWrite": true
        }
      },
      "Resources": [
        {
          "Name": "Service"
        }
      ],
      "SupportedBy": {
        "IAM Access Analyzer Policy Generation": true,
        "IAM Action Last Accessed": true
      }
    },
    {
      "Name": "CreateServiceNetwork",
      "ActionConditionKeys": [
        "aws:RequestTag/${TagKey}",
        "aws:TagKeys",
        "vpc-lattice:AuthType"
      ],
      "Annotations": {
        "Properties": {
          "IsList": false,
          "IsPermissionManagement": false,
          "IsTaggingOnly": false,
          "IsWrite": true
        }
      },
      "Resources": [
        {
          "Name": "ServiceNetwork"
        }
      ],
      "SupportedBy": {
        "IAM Access Analyzer Policy Generation": true,
        "IAM Action Last Accessed": true
      }
    },
    {
      "Name": "CreateServiceNetworkResourceAssociation",
      "ActionConditionKeys": [
        "aws:RequestTag/${TagKey}",
        "aws:TagKeys",
        "vpc-lattice:ResourceConfigurationArn",
        "vpc-lattice:ServiceNetworkArn"
      ],
      "Annotations": {
        "Properties": {
          "IsList": false,
          "IsPermissionManagement": false,
          "IsTaggingOnly": false,
          "IsWrite": true
        }
      },
      "Resources": [
        {
          "Name": "ResourceConfiguration"
        },
        {
          "Name": "ServiceNetwork"
        },
        {
          "Name": "ServiceNetworkResourceAssociation"
        }
      ],
      "SupportedBy": {
        "IAM Access Analyzer Policy Generation": true,
        "IAM Action Last Accessed": true
      }
    },
    {
      "Name": "CreateServiceNetworkServiceAssociation",
      "ActionConditionKeys": [
        "aws:RequestTag/${TagKey}",
        "aws:TagKeys",
        "vpc-lattice:ServiceArn",
        "vpc-lattice:ServiceNetworkArn"
      ],
      "Annotations": {
        "Properties": {
          "IsList": false,
          "IsPermissionManagement": false,
          "IsTaggingOnly": false,
          "IsWrite": true
        }
      },
      "Resources": [
        {
          "Name": "Service"
        },
        {
          "Name": "ServiceNetwork"
        },
        {
          "Name": "ServiceNetworkServiceAssociation"
        }
      ],
      "SupportedBy": {
        "IAM Access Analyzer Policy Generation": true,
        "IAM Action Last Accessed": true
      }
    },
    {
      "Name": "CreateServiceNetworkVpcAssociation",
      "ActionConditionKeys": [
        "aws:RequestTag/${TagKey}",
        "aws:TagKeys",
        "vpc-lattice:SecurityGroupIds",
        "vpc-lattice:ServiceNetworkArn",
        "vpc-lattice:VpcId"
      ],
      "Annotations": {
        "Properties": {
          "IsList": false,
          "IsPermissionManagement": false,
          "IsTaggingOnly": false,
          "IsWrite": true
        }
      },
      "Resources": [
        {
          "Name": "ServiceNetwork"
        },
        {
          "Name": "ServiceNetworkVpcAssociation"
        }
      ],
      "SupportedBy": {
        "IAM Access Analyzer Policy Generation": true,
        "IAM Action Last Accessed": true
      }
    },
    {
      "Name": "CreateServiceNetworkVpcEndpointAssociation",
      "Annotations": {
        "Properties": {
          "IsList": false,
          "IsPermissionManagement": true,
          "IsTaggingOnly": false,
          "IsWrite": true
        }
      },
      "SupportedBy": {
        "IAM Access Analyzer Policy Generation": false,
        "IAM Action Last Accessed": false
      }
    },
    {
      "Name": "CreateTargetGroup",
      "ActionConditionKeys": [
        "aws:RequestTag/${TagKey}",
        "aws:TagKeys",
        "vpc-lattice:VpcId"
      ],
      "Annotations": {
        "Properties": {
          "IsList": false,
          "IsPermissionManagement": false,
          "IsTaggingOnly": false,
          "IsWrite": true
        }
      },
      "Resources": [
        {
          "Name": "TargetGroup"
        }
      ],
      "SupportedBy": {
        "IAM Access Analyzer Policy Generation": true,
        "IAM Action Last Accessed": true
      }
    },
    {
      "Name": "DeleteAccessLogSubscription",
      "ActionConditionKeys": [
        "aws:ResourceTag/${TagKey}"
      ],
      "Annotations": {
        "Properties": {
          "IsList": false,
          "IsPermissionManagement": false,
          "IsTaggingOnly": false,
          "IsWrite": true
        }
      },
      "Resources": [
        {
          "Name": "AccessLogSubscription"
        }
      ],
      "SupportedBy": {
        "IAM Access Analyzer Policy Generation": true,
        "IAM Action Last Accessed": true
      }
    },
    {
      "Name": "DeleteAuthPolicy",
      "Annotations": {
        "Properties": {
          "IsList": false,
          "IsPermissionManagement": true,
          "IsTaggingOnly": false,
          "IsWrite": true
        }
      },
      "Resources": [
        {
          "Name": "Service"
        },
        {
          "Name": "ServiceNetwork"
        }
      ],
      "SupportedBy": {
        "IAM Access Analyzer Policy Generation": true,
        "IAM Action Last Accessed": true
      }
    },
    {
      "Name": "DeleteListener",
      "ActionConditionKeys": [
        "aws:ResourceTag/${TagKey}"
      ],
      "Annotations": {
        "Properties": {
          "IsList": false,
          "IsPermissionManagement": false,
          "IsTaggingOnly": false,
          "IsWrite": true
        }
      },
      "Resources": [
        {
          "Name": "Listener"
        }
      ],
      "SupportedBy": {
        "IAM Access Analyzer Policy Generation": true,
        "IAM Action Last Accessed": true
      }
    },
    {
      "Name": "DeleteResourceConfiguration",
      "ActionConditionKeys": [
        "aws:ResourceTag/${TagKey}"
      ],
      "Annotations": {
        "Properties": {
          "IsList": false,
          "IsPermissionManagement": false,
          "IsTaggingOnly": false,
          "IsWrite": true
        }
      },
      "Resources": [
        {
          "Name": "ResourceConfiguration"
        }
      ],
      "SupportedBy": {
        "IAM Access Analyzer Policy Generation": true,
        "IAM Action Last Accessed": true
      }
    },
    {
      "Name": "DeleteResourceEndpointAssociation",
      "ActionConditionKeys": [
        "aws:ResourceTag/${TagKey}"
      ],
      "Annotations": {
        "Properties": {
          "IsList": false,
          "IsPermissionManagement": false,
          "IsTaggingOnly": false,
          "IsWrite": true
        }
      },
      "Resources": [
        {
          "Name": "ResourceEndpointAssociation"
        }
      ],
      "SupportedBy": {
        "IAM Access Analyzer Policy Generation": true,
        "IAM Action Last Accessed": true
      }
    },
    {
      "Name": "DeleteResourceGateway",
      "ActionConditionKeys": [
        "aws:ResourceTag/${TagKey}"
      ],
      "Annotations": {
        "Properties": {
          "IsList": false,
          "IsPermissionManagement": false,
          "IsTaggingOnly": false,
          "IsWrite": true
        }
      },
      "Resources": [
        {
          "Name": "ResourceGateway"
        }
      ],
      "SupportedBy": {
        "IAM Access Analyzer Policy Generation": true,
        "IAM Action Last Accessed": true
      }
    },
    {
      "Name": "DeleteResourcePolicy",
      "Annotations": {
        "Properties": {
          "IsList": false,
          "IsPermissionManagement": false,
          "IsTaggingOnly": false,
          "IsWrite": true
        }
      },
      "Resources": [
        {
          "Name": "ResourceConfiguration"
        },
        {
          "Name": "Service"
        },
        {
          "Name": "ServiceNetwork"
        }
      ],
      "SupportedBy": {
        "IAM Access Analyzer Policy Generation": true,
        "IAM Action Last Accessed": true
      }
    },
    {
      "Name": "DeleteRule",
      "ActionConditionKeys": [
        "aws:ResourceTag/${TagKey}"
      ],
      "Annotations": {
        "Properties": {
          "IsList": false,
          "IsPermissionManagement": false,
          "IsTaggingOnly": false,
          "IsWrite": true
        }
      },
      "Resources": [
        {
          "Name": "Rule"
        }
      ],
      "SupportedBy": {
        "IAM Access Analyzer Policy Generation": true,
        "IAM Action Last Accessed": true
      }
    },
    {
      "Name": "DeleteService",
      "ActionConditionKeys": [
        "aws:ResourceTag/${TagKey}"
      ],
      "Annotations": {
        "Properties": {
          "IsList": false,
          "IsPermissionManagement": false,
          "IsTaggingOnly": false,
          "IsWrite": true
        }
      },
      "Resources": [
        {
          "Name": "Service"
        }
      ],
      "SupportedBy": {
        "IAM Access Analyzer Policy Generation": true,
        "IAM Action Last Accessed": true
      }
    },
    {
      "Name": "DeleteServiceNetwork",
      "ActionConditionKeys": [
        "aws:ResourceTag/${TagKey}"
      ],
      "Annotations": {
        "Properties": {
          "IsList": false,
          "IsPermissionManagement": false,
          "IsTaggingOnly": false,
          "IsWrite": true
        }
      },
      "Resources": [
        {
          "Name": "ServiceNetwork"
        }
      ],
      "SupportedBy": {
        "IAM Access Analyzer Policy Generation": true,
        "IAM Action Last Accessed": true
      }
    },
    {
      "Name": "DeleteServiceNetworkResourceAssociation",
      "ActionConditionKeys": [
        "aws:ResourceTag/${TagKey}"
      ],
      "Annotations": {
        "Properties": {
          "IsList": false,
          "IsPermissionManagement": false,
          "IsTaggingOnly": false,
          "IsWrite": true
        }
      },
      "Resources": [
        {
          "Name": "ServiceNetworkResourceAssociation"
        }
      ],
      "SupportedBy": {
        "IAM Access Analyzer Policy Generation": true,
        "IAM Action Last Accessed": true
      }
    },
    {
      "Name": "DeleteServiceNetworkServiceAssociation",
      "ActionConditionKeys": [
        "aws:ResourceTag/${TagKey}",
        "vpc-lattice:ServiceArn",
        "vpc-lattice:ServiceNetworkArn"
      ],
      "Annotations": {
        "Properties": {
          "IsList": false,
          "IsPermissionManagement": false,
          "IsTaggingOnly": false,
          "IsWrite": true
        }
      },
      "Resources": [
        {
          "Name": "ServiceNetworkServiceAssociation"
        }
      ],
      "SupportedBy": {
        "IAM Access Analyzer Policy Generation": true,
        "IAM Action Last Accessed": true
      }
    },
    {
      "Name": "DeleteServiceNetworkVpcAssociation",
      "ActionConditionKeys": [
        "aws:ResourceTag/${TagKey}",
        "vpc-lattice:ServiceNetworkArn",
        "vpc-lattice:VpcId"
      ],
      "Annotations": {
        "Properties": {
          "IsList": false,
          "IsPermissionManagement": false,
          "IsTaggingOnly": false,
          "IsWrite": true
        }
      },
      "Resources": [
        {
          "Name": "ServiceNetworkVpcAssociation"
        }
      ],
      "SupportedBy": {
        "IAM Access Analyzer Policy Generation": true,
        "IAM Action Last Accessed": true
      }
    },
    {
      "Name": "DeleteTargetGroup",
      "ActionConditionKeys": [
        "aws:ResourceTag/${TagKey}"
      ],
      "Annotations": {
        "Properties": {
          "IsList": false,
          "IsPermissionManagement": false,
          "IsTaggingOnly": false,
          "IsWrite": true
        }
      },
      "Resources": [
        {
          "Name": "TargetGroup"
        }
      ],
      "SupportedBy": {
        "IAM Access Analyzer Policy Generation": true,
        "IAM Action Last Accessed": true
      }
    },
    {
      "Name": "DeregisterTargets",
      "Annotations": {
        "Properties": {
          "IsList": false,
          "IsPermissionManagement": false,
          "IsTaggingOnly": false,
          "IsWrite": true
        }
      },
      "Resources": [
        {
          "Name": "TargetGroup"
        }
      ],
      "SupportedBy": {
        "IAM Access Analyzer Policy Generation": true,
        "IAM Action Last Accessed": true
      }
    },
    {
      "Name": "GetAccessLogSubscription",
      "ActionConditionKeys": [
        "aws:ResourceTag/${TagKey}"
      ],
      "Annotations": {
        "Properties": {
          "IsList": false,
          "IsPermissionManagement": false,
          "IsTaggingOnly": false,
          "IsWrite": false
        }
      },
      "Resources": [
        {
          "Name": "AccessLogSubscription"
        }
      ],
      "SupportedBy": {
        "IAM Access Analyzer Policy Generation": true,
        "IAM Action Last Accessed": true
      }
    },
    {
      "Name": "GetAuthPolicy",
      "Annotations": {
        "Properties": {
          "IsList": false,
          "IsPermissionManagement": false,
          "IsTaggingOnly": false,
          "IsWrite": false
        }
      },
      "Resources": [
        {
          "Name": "Service"
        },
        {
          "Name": "ServiceNetwork"
        }
      ],
      "SupportedBy": {
        "IAM Access Analyzer Policy Generation": true,
        "IAM Action Last Accessed": true
      }
    },
    {
      "Name": "GetListener",
      "ActionConditionKeys": [
        "aws:ResourceTag/${TagKey}"
      ],
      "Annotations": {
        "Properties": {
          "IsList": false,
          "IsPermissionManagement": false,
          "IsTaggingOnly": false,
          "IsWrite": false
        }
      },
      "Resources": [
        {
          "Name": "Listener"
        }
      ],
      "SupportedBy": {
        "IAM Access Analyzer Policy Generation": true,
        "IAM Action Last Accessed": true
      }
    },
    {
      "Name": "GetResourceConfiguration",
      "ActionConditionKeys": [
        "aws:ResourceTag/${TagKey}"
      ],
      "Annotations": {
        "Properties": {
          "IsList": false,
          "IsPermissionManagement": false,
          "IsTaggingOnly": false,
          "IsWrite": false
        }
      },
      "Resources": [
        {
          "Name": "ResourceConfiguration"
        }
      ],
      "SupportedBy": {
        "IAM Access Analyzer Policy Generation": true,
        "IAM Action Last Accessed": true
      }
    },
    {
      "Name": "GetResourceGateway",
      "ActionConditionKeys": [
        "aws:ResourceTag/${TagKey}"
      ],
      "Annotations": {
        "Properties": {
          "IsList": false,
          "IsPermissionManagement": false,
          "IsTaggingOnly": false,
          "IsWrite": false
        }
      },
      "Resources": [
        {
          "Name": "ResourceGateway"
        }
      ],
      "SupportedBy": {
        "IAM Access Analyzer Policy Generation": true,
        "IAM Action Last Accessed": true
      }
    },
    {
      "Name": "GetResourcePolicy",
      "Annotations": {
        "Properties": {
          "IsList": false,
          "IsPermissionManagement": false,
          "IsTaggingOnly": false,
          "IsWrite": false
        }
      },
      "Resources": [
        {
          "Name": "ResourceConfiguration"
        },
        {
          "Name": "Service"
        },
        {
          "Name": "ServiceNetwork"
        }
      ],
      "SupportedBy": {
        "IAM Access Analyzer Policy Generation": true,
        "IAM Action Last Accessed": true
      }
    },
    {
      "Name": "GetRule",
      "ActionConditionKeys": [
        "aws:ResourceTag/${TagKey}"
      ],
      "Annotations": {
        "Properties": {
          "IsList": false,
          "IsPermissionManagement": false,
          "IsTaggingOnly": false,
          "IsWrite": false
        }
      },
      "Resources": [
        {
          "Name": "Rule"
        }
      ],
      "SupportedBy": {
        "IAM Access Analyzer Policy Generation": true,
        "IAM Action Last Accessed": true
      }
    },
    {
      "Name": "GetService",
      "ActionConditionKeys": [
        "aws:ResourceTag/${TagKey}"
      ],
      "Annotations": {
        "Properties": {
          "IsList": false,
          "IsPermissionManagement": false,
          "IsTaggingOnly": false,
          "IsWrite": false
        }
      },
      "Resources": [
        {
          "Name": "Service"
        }
      ],
      "SupportedBy": {
        "IAM Access Analyzer Policy Generation": true,
        "IAM Action Last Accessed": true
      }
    },
    {
      "Name": "GetServiceNetwork",
      "ActionConditionKeys": [
        "aws:ResourceTag/${TagKey}"
      ],
      "Annotations": {
        "Properties": {
          "IsList": false,
          "IsPermissionManagement": false,
          "IsTaggingOnly": false,
          "IsWrite": false
        }
      },
      "Resources": [
        {
          "Name": "ServiceNetwork"
        }
      ],
      "SupportedBy": {
        "IAM Access Analyzer Policy Generation": true,
        "IAM Action Last Accessed": true
      }
    },
    {
      "Name": "GetServiceNetworkResourceAssociation",
      "ActionConditionKeys": [
        "aws:ResourceTag/${TagKey}"
      ],
      "Annotations": {
        "Properties": {
          "IsList": false,
          "IsPermissionManagement": false,
          "IsTaggingOnly": false,
          "IsWrite": false
        }
      },
      "Resources": [
        {
          "Name": "ServiceNetworkResourceAssociation"
        }
      ],
      "SupportedBy": {
        "IAM Access Analyzer Policy Generation": true,
        "IAM Action Last Accessed": true
      }
    },
    {
      "Name": "GetServiceNetworkServiceAssociation",
      "ActionConditionKeys": [
        "aws:ResourceTag/${TagKey}",
        "vpc-lattice:ServiceArn",
        "vpc-lattice:ServiceNetworkArn"
      ],
      "Annotations": {
        "Properties": {
          "IsList": false,
          "IsPermissionManagement": false,
          "IsTaggingOnly": false,
          "IsWrite": false
        }
      },
      "Resources": [
        {
          "Name": "ServiceNetworkServiceAssociation"
        }
      ],
      "SupportedBy": {
        "IAM Access Analyzer Policy Generation": true,
        "IAM Action Last Accessed": true
      }
    },
    {
      "Name": "GetServiceNetworkVpcAssociation",
      "ActionConditionKeys": [
        "aws:ResourceTag/${TagKey}",
        "vpc-lattice:ServiceNetworkArn",
        "vpc-lattice:VpcId"
      ],
      "Annotations": {
        "Properties": {
          "IsList": false,
          "IsPermissionManagement": false,
          "IsTaggingOnly": false,
          "IsWrite": false
        }
      },
      "Resources": [
        {
          "Name": "ServiceNetworkVpcAssociation"
        }
      ],
      "SupportedBy": {
        "IAM Access Analyzer Policy Generation": true,
        "IAM Action Last Accessed": true
      }
    },
    {
      "Name": "GetTargetGroup",
      "ActionConditionKeys": [
        "aws:ResourceTag/${TagKey}"
      ],
      "Annotations": {
        "Properties": {
          "IsList": false,
          "IsPermissionManagement": false,
          "IsTaggingOnly": false,
          "IsWrite": false
        }
      },
      "Resources": [
        {
          "Name": "TargetGroup"
        }
      ],
      "SupportedBy": {
        "IAM Access Analyzer Policy Generation": true,
        "IAM Action Last Accessed": true
      }
    },
    {
      "Name": "ListAccessLogSubscriptions",
      "Annotations": {
        "Properties": {
          "IsList": true,
          "IsPermissionManagement": false,
          "IsTaggingOnly": false,
          "IsWrite": false
        }
      },
      "SupportedBy": {
        "IAM Access Analyzer Policy Generation": true,
        "IAM Action Last Accessed": true
      }
    },
    {
      "Name": "ListListeners",
      "Annotations": {
        "Properties": {
          "IsList": true,
          "IsPermissionManagement": false,
          "IsTaggingOnly": false,
          "IsWrite": false
        }
      },
      "SupportedBy": {
        "IAM Access Analyzer Policy Generation": true,
        "IAM Action Last Accessed": true
      }
    },
    {
      "Name": "ListResourceConfigurations",
      "Annotations": {
        "Properties": {
          "IsList": true,
          "IsPermissionManagement": false,
          "IsTaggingOnly": false,
          "IsWrite": false
        }
      },
      "SupportedBy": {
        "IAM Access Analyzer Policy Generation": true,
        "IAM Action Last Accessed": true
      }
    },
    {
      "Name": "ListResourceEndpointAssociations",
      "ActionConditionKeys": [
        "vpc-lattice:ResourceConfigurationArn",
        "vpc-lattice:VpcEndpointId"
      ],
      "Annotations": {
        "Properties": {
          "IsList": true,
          "IsPermissionManagement": false,
          "IsTaggingOnly": false,
          "IsWrite": false
        }
      },
      "SupportedBy": {
        "IAM Access Analyzer Policy Generation": true,
        "IAM Action Last Accessed": true
      }
    },
    {
      "Name": "ListResourceGateways",
      "Annotations": {
        "Properties": {
          "IsList": true,
          "IsPermissionManagement": false,
          "IsTaggingOnly": false,
          "IsWrite": false
        }
      },
      "SupportedBy": {
        "IAM Access Analyzer Policy Generation": true,
        "IAM Action Last Accessed": true
      }
    },
    {
      "Name": "ListRules",
      "Annotations": {
        "Properties": {
          "IsList": true,
          "IsPermissionManagement": false,
          "IsTaggingOnly": false,
          "IsWrite": false
        }
      },
      "SupportedBy": {
        "IAM Access Analyzer Policy Generation": true,
        "IAM Action Last Accessed": true
      }
    },
    {
      "Name": "ListServiceNetworkResourceAssociations",
      "Annotations": {
        "Properties": {
          "IsList": true,
          "IsPermissionManagement": false,
          "IsTaggingOnly": false,
          "IsWrite": false
        }
      },
      "SupportedBy": {
        "IAM Access Analyzer Policy Generation": true,
        "IAM Action Last Accessed": true
      }
    },
    {
      "Name": "ListServiceNetworkServiceAssociations",
      "ActionConditionKeys": [
        "vpc-lattice:ServiceArn",
        "vpc-lattice:ServiceNetworkArn"
      ],
      "Annotations": {
        "Properties": {
          "IsList": true,
          "IsPermissionManagement": false,
          "IsTaggingOnly": false,
          "IsWrite": false
        }
      },
      "SupportedBy": {
        "IAM Access Analyzer Policy Generation": true,
        "IAM Action Last Accessed": true
      }
    },
    {
      "Name": "ListServiceNetworkVpcAssociations",
      "ActionConditionKeys": [
        "vpc-lattice:ServiceNetworkArn",
        "vpc-lattice:VpcId"
      ],
      "Annotations": {
        "Properties": {
          "IsList": true,
          "IsPermissionManagement": false,
          "IsTaggingOnly": false,
          "IsWrite": false
        }
      },
      "SupportedBy": {
        "IAM Access Analyzer Policy Generation": true,
        "IAM Action Last Accessed": true
      }
    },
    {
      "Name": "ListServiceNetworkVpcEndpointAssociations",
      "Annotations": {
        "Properties": {
          "IsList": true,
          "IsPermissionManagement": false,
          "IsTaggingOnly": false,
          "IsWrite": false
        }
      },
      "SupportedBy": {
        "IAM Access Analyzer Policy Generation": true,
        "IAM Action Last Accessed": true
      }
    },
    {
      "Name": "ListServiceNetworks",
      "Annotations": {
        "Properties": {
          "IsList": true,
          "IsPermissionManagement": false,
          "IsTaggingOnly": false,
          "IsWrite": false
        }
      },
      "SupportedBy": {
        "IAM Access Analyzer Policy Generation": true,
        "IAM Action Last Accessed": true
      }
    },
    {
      "Name": "ListServices",
      "Annotations": {
        "Properties": {
          "IsList": true,
          "IsPermissionManagement": false,
          "IsTaggingOnly": false,
          "IsWrite": false
        }
      },
      "SupportedBy": {
        "IAM Access Analyzer Policy Generation": true,
        "IAM Action Last Accessed": true
      }
    },
    {
      "Name": "ListTagsForResource",
      "Annotations": {
        "Properties": {
          "IsList": false,
          "IsPermissionManagement": false,
          "IsTaggingOnly": false,
          "IsWrite": false
        }
      },
      "SupportedBy": {
        "IAM Access Analyzer Policy Generation": true,
        "IAM Action Last Accessed": false
      }
    },
    {
      "Name": "ListTargetGroups",
      "Annotations": {
        "Properties": {
          "IsList": true,
          "IsPermissionManagement": false,
          "IsTaggingOnly": false,
          "IsWrite": false
        }
      },
      "SupportedBy": {
        "IAM Access Analyzer Policy Generation": true,
        "IAM Action Last Accessed": true
      }
    },
    {
      "Name": "ListTargets",
      "Annotations": {
        "Properties": {
          "IsList": true,
          "IsPermissionManagement": false,
          "IsTaggingOnly": false,
          "IsWrite": false
        }
      },
      "Resources": [
        {
          "Name": "TargetGroup"
        }
      ],
      "SupportedBy": {
        "IAM Access Analyzer Policy Generation": true,
        "IAM Action Last Accessed": true
      }
    },
    {
      "Name": "PutAuthPolicy",
      "Annotations": {
        "Properties": {
          "IsList": false,
          "IsPermissionManagement": true,
          "IsTaggingOnly": false,
          "IsWrite": true
        }
      },
      "Resources": [
        {
          "Name": "Service"
        },
        {
          "Name": "ServiceNetwork"
        }
      ],
      "SupportedBy": {
        "IAM Access Analyzer Policy Generation": true,
        "IAM Action Last Accessed": true
      }
    },
    {
      "Name": "PutResourcePolicy",
      "Annotations": {
        "Properties": {
          "IsList": false,
          "IsPermissionManagement": false,
          "IsTaggingOnly": false,
          "IsWrite": true
        }
      },
      "Resources": [
        {
          "Name": "ResourceConfiguration"
        },
        {
          "Name": "Service"
        },
        {
          "Name": "ServiceNetwork"
        }
      ],
      "SupportedBy": {
        "IAM Access Analyzer Policy Generation": true,
        "IAM Action Last Accessed": true
      }
    },
    {
      "Name": "RegisterTargets",
      "Annotations": {
        "Properties": {
          "IsList": false,
          "IsPermissionManagement": false,
          "IsTaggingOnly": false,
          "IsWrite": true
        }
      },
      "Resources": [
        {
          "Name": "TargetGroup"
        }
      ],
      "SupportedBy": {
        "IAM Access Analyzer Policy Generation": true,
        "IAM Action Last Accessed": true
      }
    },
    {
      "Name": "TagResource",
      "ActionConditionKeys": [
        "aws:RequestTag/${TagKey}",
        "aws:ResourceTag/${TagKey}",
        "aws:TagKeys"
      ],
      "Annotations": {
        "Properties": {
          "IsList": false,
          "IsPermissionManagement": false,
          "IsTaggingOnly": true,
          "IsWrite": true
        }
      },
      "Resources": [
        {
          "Name": "AccessLogSubscription"
        },
        {
          "Name": "Listener"
        },
        {
          "Name": "ResourceConfiguration"
        },
        {
          "Name": "ResourceEndpointAssociation"
        },
        {
          "Name": "ResourceGateway"
        },
        {
          "Name": "Rule"
        },
        {
          "Name": "Service"
        },
        {
          "Name": "ServiceNetwork"
        },
        {
          "Name": "ServiceNetworkResourceAssociation"
        },
        {
          "Name": "ServiceNetworkServiceAssociation"
        },
        {
          "Name": "ServiceNetworkVpcAssociation"
        },
        {
          "Name": "TargetGroup"
        }
      ],
      "SupportedBy": {
        "IAM Access Analyzer Policy Generation": true,
        "IAM Action Last Accessed": false
      }
    },
    {
      "Name": "UntagResource",
      "ActionConditionKeys": [
        "aws:TagKeys"
      ],
      "Annotations": {
        "Properties": {
          "IsList": false,
          "IsPermissionManagement": false,
          "IsTaggingOnly": true,
          "IsWrite": true
        }
      },
      "Resources": [
        {
          "Name": "AccessLogSubscription"
        },
        {
          "Name": "Listener"
        },
        {
          "Name": "ResourceConfiguration"
        },
        {
          "Name": "ResourceEndpointAssociation"
        },
        {
          "Name": "ResourceGateway"
        },
        {
          "Name": "Rule"
        },
        {
          "Name": "Service"
        },
        {
          "Name": "ServiceNetwork"
        },
        {
          "Name": "ServiceNetworkResourceAssociation"
        },
        {
          "Name": "ServiceNetworkServiceAssociation"
        },
        {
          "Name": "ServiceNetworkVpcAssociation"
        },
        {
          "Name": "TargetGroup"
        }
      ],
      "SupportedBy": {
        "IAM Access Analyzer Policy Generation": true,
        "IAM Action Last Accessed": false
      }
    },
    {
      "Name": "UpdateAccessLogSubscription",
      "ActionConditionKeys": [
        "aws:ResourceTag/${TagKey}"
      ],
      "Annotations": {
        "Properties": {
          "IsList": false,
          "IsPermissionManagement": false,
          "IsTaggingOnly": false,
          "IsWrite": true
        }
      },
      "Resources": [
        {
          "Name": "AccessLogSubscription"
        }
      ],
      "SupportedBy": {
        "IAM Access Analyzer Policy Generation": true,
        "IAM Action Last Accessed": true
      }
    },
    {
      "Name": "UpdateListener",
      "ActionConditionKeys": [
        "aws:ResourceTag/${TagKey}",
        "vpc-lattice:TargetGroupArns"
      ],
      "Annotations": {
        "Properties": {
          "IsList": false,
          "IsPermissionManagement": false,
          "IsTaggingOnly": false,
          "IsWrite": true
        }
      },
      "Resources": [
        {
          "Name": "Listener"
        }
      ],
      "SupportedBy": {
        "IAM Access Analyzer Policy Generation": true,
        "IAM Action Last Accessed": true
      }
    },
    {
      "Name": "UpdateResourceConfiguration",
      "ActionConditionKeys": [
        "aws:ResourceTag/${TagKey}"
      ],
      "Annotations": {
        "Properties": {
          "IsList": false,
          "IsPermissionManagement": false,
          "IsTaggingOnly": false,
          "IsWrite": true
        }
      },
      "Resources": [
        {
          "Name": "ResourceConfiguration"
        }
      ],
      "SupportedBy": {
        "IAM Access Analyzer Policy Generation": true,
        "IAM Action Last Accessed": true
      }
    },
    {
      "Name": "UpdateResourceGateway",
      "ActionConditionKeys": [
        "aws:ResourceTag/${TagKey}",
        "vpc-lattice:SecurityGroupIds"
      ],
      "Annotations": {
        "Properties": {
          "IsList": false,
          "IsPermissionManagement": false,
          "IsTaggingOnly": false,
          "IsWrite": true
        }
      },
      "Resources": [
        {
          "Name": "ResourceGateway"
        }
      ],
      "SupportedBy": {
        "IAM Access Analyzer Policy Generation": true,
        "IAM Action Last Accessed": true
      }
    },
    {
      "Name": "UpdateRule",
      "ActionConditionKeys": [
        "aws:ResourceTag/${TagKey}",
        "vpc-lattice:TargetGroupArns"
      ],
      "Annotations": {
        "Properties": {
          "IsList": false,
          "IsPermissionManagement": false,
          "IsTaggingOnly": false,
          "IsWrite": true
        }
      },
      "Resources": [
        {
          "Name": "Rule"
        }
      ],
      "SupportedBy": {
        "IAM Access Analyzer Policy Generation": true,
        "IAM Action Last Accessed": true
      }
    },
    {
      "Name": "UpdateService",
      "ActionConditionKeys": [
        "aws:ResourceTag/${TagKey}",
        "vpc-lattice:AuthType"
      ],
      "Annotations": {
        "Properties": {
          "IsList": false,
          "IsPermissionManagement": false,
          "IsTaggingOnly": false,
          "IsWrite": true
        }
      },
      "Resources": [
        {
          "Name": "Service"
        }
      ],
      "SupportedBy": {
        "IAM Access Analyzer Policy Generation": true,
        "IAM Action Last Accessed": true
      }
    },
    {
      "Name": "UpdateServiceNetwork",
      "ActionConditionKeys": [
        "aws:ResourceTag/${TagKey}",
        "vpc-lattice:AuthType"
      ],
      "Annotations": {
        "Properties": {
          "IsList": false,
          "IsPermissionManagement": false,
          "IsTaggingOnly": false,
          "IsWrite": true
        }
      },
      "Resources": [
        {
          "Name": "ServiceNetwork"
        }
      ],
      "SupportedBy": {
        "IAM Access Analyzer Policy Generation": true,
        "IAM Action Last Accessed": true
      }
    },
    {
      "Name": "UpdateServiceNetworkVpcAssociation",
      "ActionConditionKeys": [
        "aws:ResourceTag/${TagKey}",
        "aws:TagKeys",
        "vpc-lattice:SecurityGroupIds",
        "vpc-lattice:ServiceNetworkArn",
        "vpc-lattice:VpcId"
      ],
      "Annotations": {
        "Properties": {
          "IsList": false,
          "IsPermissionManagement": false,
          "IsTaggingOnly": false,
          "IsWrite": true
        }
      },
      "Resources": [
        {
          "Name": "ServiceNetworkVpcAssociation"
        }
      ],
      "SupportedBy": {
        "IAM Access Analyzer Policy Generation": true,
        "IAM Action Last Accessed": true
      }
    },
    {
      "Name": "UpdateTargetGroup",
      "ActionConditionKeys": [
        "aws:ResourceTag/${TagKey}"
      ],
      "Annotations": {
        "Properties": {
          "IsList": false,
          "IsPermissionManagement": false,
          "IsTaggingOnly": false,
          "IsWrite": true
        }
      },
      "Resources": [
        {
          "Name": "TargetGroup"
        }
      ],
      "SupportedBy": {
        "IAM Access Analyzer Policy Generation": true,
        "IAM Action Last Accessed": true
      }
    }
  ],
  "ConditionKeys": [
    {
      "Name": "aws:RequestTag/${TagKey}",
      "Types": [
        "String"
      ]
    },
    {
      "Name": "aws:ResourceTag/${TagKey}",
      "Types": [
        "String"
      ]
    },
    {
      "Name": "aws:TagKeys",
      "Types": [
        "ArrayOfString"
      ]
    },
    {
      "Name": "vpc-lattice:AuthType",
      "Types": [
        "String"
      ]
    },
    {
      "Name": "vpc-lattice:Protocol",
      "Types": [
        "String"
      ]
    },
    {
      "Name": "vpc-lattice:ResourceConfigurationArn",
      "Types": [
        "ARN"
      ]
    },
    {
      "Name": "vpc-lattice:SecurityGroupIds",
      "Types": [
        "ArrayOfString"
      ]
    },
    {
      "Name": "vpc-lattice:ServiceArn",
      "Types": [
        "ARN"
      ]
    },
    {
      "Name": "vpc-lattice:ServiceNetworkArn",
      "Types": [
        "ARN"
      ]
    },
    {
      "Name": "vpc-lattice:TargetGroupArns",
      "Types": [
        "ArrayOfARN"
      ]
    },
    {
      "Name": "vpc-lattice:VpcEndpointId",
      "Types": [
        "String"
      ]
    },
    {
      "Name": "vpc-lattice:VpcId",
      "Types": [
        "String"
      ]
    }
  ],
  "Resources": [
    {
      "Name": "AccessLogSubscription",
      "ARNFormats": [
        "arn:${Partition}:vpc-lattice:${Region}:${Account}:accesslogsubscription/${AccessLogSubscriptionId}"
      ],
      "ConditionKeys": [
        "aws:RequestTag/${TagKey}",
        "aws:ResourceTag/${TagKey}",
        "aws:TagKeys"
      ]
    },
    {
      "Name": "Listener",
      "ARNFormats": [
        "arn:${Partition}:vpc-lattice:${Region}:${Account}:service/${ServiceId}/listener/${ListenerId}"
      ],
      "ConditionKeys": [
        "aws:RequestTag/${TagKey}",
        "aws:ResourceTag/${TagKey}",
        "aws:TagKeys",
        "vpc-lattice:Protocol",
        "vpc-lattice:TargetGroupArns"
      ]
    },
    {
      "Name": "ResourceConfiguration",
      "ARNFormats": [
        "arn:${Partition}:vpc-lattice:${Region}:${Account}:resourceconfiguration/${ResourceConfigurationId}"
      ],
      "ConditionKeys": [
        "aws:RequestTag/${TagKey}",
        "aws:ResourceTag/${TagKey}",
        "aws:TagKeys"
      ]
    },
    {
      "Name": "ResourceEndpointAssociation",
      "ARNFormats": [
        "arn:${Partition}:vpc-lattice:${Region}:${Account}:resourceendpointassociation/${ResourceEndpointAssociationId}"
      ],
      "ConditionKeys": [
        "aws:RequestTag/${TagKey}",
        "aws:ResourceTag/${TagKey}",
        "aws:TagKeys",
        "vpc-lattice:ResourceConfigurationArn",
        "vpc-lattice:VpcEndpointId"
      ]
    },
    {
      "Name": "ResourceGateway",
      "ARNFormats": [
        "arn:${Partition}:vpc-lattice:${Region}:${Account}:resourcegateway/${ResourceGatewayId}"
      ],
      "ConditionKeys": [
        "aws:RequestTag/${TagKey}",
        "aws:ResourceTag/${TagKey}",
        "aws:TagKeys",
        "vpc-lattice:VpcId"
      ]
    },
    {
      "Name": "Rule",
      "ARNFormats": [
        "arn:${Partition}:vpc-lattice:${Region}:${Account}:service/${ServiceId}/listener/${ListenerId}/rule/${RuleId}"
      ],
      "ConditionKeys": [
        "aws:RequestTag/${TagKey}",
        "aws:ResourceTag/${TagKey}",
        "aws:TagKeys",
        "vpc-lattice:TargetGroupArns"
      ]
    },
    {
      "Name": "Service",
      "ARNFormats": [
        "arn:${Partition}:vpc-lattice:${Region}:${Account}:service/${ServiceId}"
      ],
      "ConditionKeys": [
        "aws:RequestTag/${TagKey}",
        "aws:ResourceTag/${TagKey}",
        "aws:TagKeys",
        "vpc-lattice:AuthType"
      ]
    },
    {
      "Name": "ServiceNetwork",
      "ARNFormats": [
        "arn:${Partition}:vpc-lattice:${Region}:${Account}:servicenetwork/${ServiceNetworkId}"
      ],
      "ConditionKeys": [
        "aws:RequestTag/${TagKey}",
        "aws:ResourceTag/${TagKey}",
        "aws:TagKeys",
        "vpc-lattice:AuthType"
      ]
    },
    {
      "Name": "ServiceNetworkResourceAssociation",
      "ARNFormats": [
        "arn:${Partition}:vpc-lattice:${Region}:${Account}:servicenetworkresourceassociation/${ServiceNetworkResourceAssociationId}"
      ],
      "ConditionKeys": [
        "aws:RequestTag/${TagKey}",
        "aws:ResourceTag/${TagKey}",
        "aws:TagKeys",
        "vpc-lattice:ResourceConfigurationArn",
        "vpc-lattice:ServiceNetworkArn"
      ]
    },
    {
      "Name": "ServiceNetworkServiceAssociation",
      "ARNFormats": [
        "arn:${Partition}:vpc-lattice:${Region}:${Account}:servicenetworkserviceassociation/${ServiceNetworkServiceAssociationId}"
      ],
      "ConditionKeys": [
        "aws:RequestTag/${TagKey}",
        "aws:ResourceTag/${TagKey}",
        "aws:TagKeys",
        "vpc-lattice:ServiceArn",
        "vpc-lattice:ServiceNetworkArn"
      ]
    },
    {
      "Name": "ServiceNetworkVpcAssociation",
      "ARNFormats": [
        "arn:${Partition}:vpc-lattice:${Region}:${Account}:servicenetworkvpcassociation/${ServiceNetworkVpcAssociationId}"
      ],
      "ConditionKeys": [
        "aws:RequestTag/${TagKey}",
        "aws:ResourceTag/${TagKey}",
        "aws:TagKeys",
        "vpc-lattice:SecurityGroupIds",
        "vpc-lattice:ServiceNetworkArn",
        "vpc-lattice:VpcId"
      ]
    },
    {
      "Name": "TargetGroup",
      "ARNFormats": [
        "arn:${Partition}:vpc-lattice:${Region}:${Account}:targetgroup/${TargetGroupId}"
      ],
      "ConditionKeys": [
        "aws:RequestTag/${TagKey}",
        "aws:ResourceTag/${TagKey}",
        "aws:TagKeys",
        "vpc-lattice:VpcId"
      ]
    }
  ],
  "Version": "v1.3"
}