<?xml version="1.0" encoding="utf-8"?>
<odoo>
  <data>
    <record id="partner_action_tag_view_tree" model="ir.ui.view">
      <field name="name">somconnexio.partner_action_tag.tree</field>
      <field name="model">partner.action.tag</field>
      <field name="groups_id" eval="[(6,0,[ref('somconnexio.group_somconnexio_admin')])]"/>
      <field name="arch" type="xml">
        <tree editable="bottom">
          <field name="name"/>
          <field name="code"/>
        </tree>
      </field>
    </record>
    <record id="partner_action_tags_action" model="ir.actions.act_window">
      <field name="name">Partner action tags</field>
      <field name="res_model">partner.action.tag</field>
      <field name="view_mode">tree</field>
    </record>
    <menuitem name="Partner Action Tags" id="menu_partner_action_tags" action="partner_action_tags_action" parent="contacts.res_partner_menu_config" sequence="2"/>
  </data>
</odoo>
