<?xml version="1.0" encoding="utf-8"?>
<odoo>
  <data noupdate="0">
    <record id="ADSL20MB100MinFixMobile" model="product.product">
      <field name="product_template_attribute_value_ids" search="[('product_attribute_value_id', 'in', [ref('100MinFixIMobile'),ref('20Mb')]),('product_tmpl_id', '=', ref('ADSL_product_template'))]"/>
      <field name="product_tmpl_id" ref="ADSL_product_template"/>
      <field name="default_code">SE_SC_REC_BA_ADSL_100</field>
      <field name="custom_name">ADSL 100 min a fix o mòbil</field>
    </record>
    <record id="ADSL20MB1000MinFix" model="product.product">
      <field name="product_template_attribute_value_ids" search="[('product_attribute_value_id', 'in', [ref('1000MinFix'),ref('20Mb')]),('product_tmpl_id', '=', ref('ADSL_product_template'))]"/>
      <field name="product_tmpl_id" ref="ADSL_product_template"/>
      <field name="default_code">SE_SC_REC_BA_ADSL_1000</field>
      <field name="custom_name">ADSL 1000 min a fix</field>
    </record>
    <record id="ADSL20MBSenseFix" model="product.product">
      <field name="product_template_attribute_value_ids" search="[('product_attribute_value_id', 'in', [ref('SenseFix'),ref('20Mb')]),('product_tmpl_id', '=', ref('ADSL_product_template'))]"/>
      <field name="product_tmpl_id" ref="ADSL_product_template"/>
      <field name="default_code">SE_SC_REC_BA_ADSL_SF</field>
      <field name="custom_name">20Mb sense telèfon fix</field>
      <field name="without_fix" eval="True"/>
    </record>
    <record id="ADSL20MBLaBordaLocalFibra" model="product.product">
      <field name="name">Servei fibra La Borda Baixos</field>
      <field name="default_code">SE_SC_REC_BA_BORDA_LOCAL</field>
      <field name="custom_name">La Borda servei fibra local</field>
    </record>
    <record id="ADSL20MBLaBordaFibra" model="product.product">
      <field name="name">Servei fibra La Borda</field>
      <field name="default_code">SE_SC_REC_BA_BORDA</field>
      <field name="custom_name">La Borda servei fibra</field>
    </record>
    <record id="ADSL20MBLaBordaManteniment" model="product.product">
      <field name="name">Quota manteniment fibra La Borda (OPEX)</field>
      <field name="default_code">SE_SC_REC_BA_BORDA_MANTENIMENT</field>
      <field name="custom_name">La Borda quota manteniment fibra</field>
    </record>
    <record id="ADSL20MBLaBordaIPfixa" model="product.product">
      <field name="name">IPv4 Fixa</field>
      <field name="default_code">SE_SC_REC_MOBILE_BA_IP_fix</field>
      <field name="custom_name">La Borda IP fixa</field>
    </record>
  </data>
</odoo>
